<?xml version="1.0" encoding="UTF-8" standalone="no" ?><!DOCTYPE dataset SYSTEM "binning.dtd"><?xml-stylesheet type="text/xsl" href="binning.xsl"?><binning>
        <!-- eta jet -->
        <bin id="1" type="inlcusive">
                <subbin>
                        <variable>etajet</variable>
                        <low_edge>-1.6</low_edge>
                        <up_edge>2.2</up_edge>
                </subbin>
                <k_uds>0.912311</k_uds>
                <k_c>1.23279</k_c>
                <k_b>1.49805</k_b>
                <k_uds_err>0.00468418</k_uds_err>
                <k_c_err>0.019032</k_c_err>
                <k_b_err>0.051933</k_b_err>
                <sigma_uds_true>0</sigma_uds_true>
                <sigma_c_true>14090.3</sigma_c_true>
                <sigma_b_true>676.917</sigma_b_true>
                <sigma_uds>0</sigma_uds>
                <sigma_c>4571.15</sigma_c>
                <sigma_b>266.856</sigma_b>
                <sigma_uds_err>0</sigma_uds_err>
                <sigma_c_err>70.5704</sigma_c_err>
                <sigma_b_err>9.25113</sigma_b_err>
        </bin>
        <bin_group id="etajet">
        <bin id="2">
                <subbin>
                        <variable>etajet</variable>
                        <low_edge>-1.6</low_edge>
                        <up_edge>-1.1</up_edge>
                </subbin>
                <k_uds>0.91084</k_uds>
                <k_c>1.09416</k_c>
                <k_b>2.28571</k_b>
                <k_uds_err>0.0308688</k_uds_err>
                <k_c_err>0.134197</k_c_err>
                <k_b_err>1.7979</k_b_err>
                <sigma_uds_true>0</sigma_uds_true>
                <sigma_c_true>960.79</sigma_c_true>
                <sigma_b_true>38.2263</sigma_b_true>
                <sigma_uds>0</sigma_uds>
                <sigma_c>2102.52</sigma_c>
                <sigma_b>174.748</sigma_b>
                <sigma_uds_err>0</sigma_uds_err>
                <sigma_c_err>257.871</sigma_c_err>
                <sigma_b_err>137.454</sigma_b_err>
        </bin>
        <bin id="3">
                <subbin>
                        <variable>etajet</variable>
                        <low_edge>-1.1</low_edge>
                        <up_edge>-0.8</up_edge>
                </subbin>
                <k_uds>0.968287</k_uds>
                <k_c>1.10081</k_c>
                <k_b>1.46687</k_b>
                <k_uds_err>0.0188592</k_uds_err>
                <k_c_err>0.0671166</k_c_err>
                <k_b_err>0.377467</k_b_err>
                <sigma_uds_true>0</sigma_uds_true>
                <sigma_c_true>996.233</sigma_c_true>
                <sigma_b_true>44.6703</sigma_b_true>
                <sigma_uds>0</sigma_uds>
                <sigma_c>3655.54</sigma_c>
                <sigma_b>218.418</sigma_b>
                <sigma_uds_err>0</sigma_uds_err>
                <sigma_c_err>222.879</sigma_c_err>
                <sigma_b_err>56.2051</sigma_b_err>
        </bin>
        <bin id="4">
                <subbin>
                        <variable>etajet</variable>
                        <low_edge>-0.8</low_edge>
                        <up_edge>-0.5</up_edge>
                </subbin>
                <k_uds>0.978863</k_uds>
                <k_c>1.10166</k_c>
                <k_b>1.47963</k_b>
                <k_uds_err>0.0145178</k_uds_err>
                <k_c_err>0.0493089</k_c_err>
                <k_b_err>0.178533</k_b_err>
                <sigma_uds_true>0</sigma_uds_true>
                <sigma_c_true>1249.82</sigma_c_true>
                <sigma_b_true>54.086</sigma_b_true>
                <sigma_uds>0</sigma_uds>
                <sigma_c>4589.59</sigma_c>
                <sigma_b>266.758</sigma_b>
                <sigma_uds_err>0</sigma_uds_err>
                <sigma_c_err>205.425</sigma_c_err>
                <sigma_b_err>32.1871</sigma_b_err>
        </bin>
        <bin id="5">
                <subbin>
                        <variable>etajet</variable>
                        <low_edge>-0.5</low_edge>
                        <up_edge>-0.2</up_edge>
                </subbin>
                <k_uds>0.946545</k_uds>
                <k_c>1.1753</k_c>
                <k_b>1.17659</k_b>
                <k_uds_err>0.0125511</k_uds_err>
                <k_c_err>0.0429656</k_c_err>
                <k_b_err>0.120909</k_b_err>
                <sigma_uds_true>0</sigma_uds_true>
                <sigma_c_true>1427.93</sigma_c_true>
                <sigma_b_true>58.0454</sigma_b_true>
                <sigma_uds>0</sigma_uds>
                <sigma_c>5594.17</sigma_c>
                <sigma_b>227.652</sigma_b>
                <sigma_uds_err>0</sigma_uds_err>
                <sigma_c_err>204.506</sigma_c_err>
                <sigma_b_err>23.3939</sigma_b_err>
        </bin>
        <bin id="6">
                <subbin>
                        <variable>etajet</variable>
                        <low_edge>-0.2</low_edge>
                        <up_edge>0.1</up_edge>
                </subbin>
                <k_uds>0.966083</k_uds>
                <k_c>1.12228</k_c>
                <k_b>1.48349</k_b>
                <k_uds_err>0.0123657</k_uds_err>
                <k_c_err>0.0432493</k_c_err>
                <k_b_err>0.106354</k_b_err>
                <sigma_uds_true>0</sigma_uds_true>
                <sigma_c_true>1515.19</sigma_c_true>
                <sigma_b_true>60.936</sigma_b_true>
                <sigma_uds>0</sigma_uds>
                <sigma_c>5668.23</sigma_c>
                <sigma_b>301.326</sigma_b>
                <sigma_uds_err>0</sigma_uds_err>
                <sigma_c_err>218.437</sigma_c_err>
                <sigma_b_err>21.6026</sigma_b_err>
        </bin>
        <bin id="7">
                <subbin>
                        <variable>etajet</variable>
                        <low_edge>0.1</low_edge>
                        <up_edge>0.4</up_edge>
                </subbin>
                <k_uds>0.951136</k_uds>
                <k_c>1.24278</k_c>
                <k_b>1.3961</k_b>
                <k_uds_err>0.0124169</k_uds_err>
                <k_c_err>0.0451351</k_c_err>
                <k_b_err>0.103288</k_b_err>
                <sigma_uds_true>0</sigma_uds_true>
                <sigma_c_true>1509.57</sigma_c_true>
                <sigma_b_true>64.2928</sigma_b_true>
                <sigma_uds>0</sigma_uds>
                <sigma_c>6253.54</sigma_c>
                <sigma_b>299.198</sigma_b>
                <sigma_uds_err>0</sigma_uds_err>
                <sigma_c_err>227.115</sigma_c_err>
                <sigma_b_err>22.1355</sigma_b_err>
        </bin>
        <bin id="8">
                <subbin>
                        <variable>etajet</variable>
                        <low_edge>0.4</low_edge>
                        <up_edge>0.7</up_edge>
                </subbin>
                <k_uds>0.966996</k_uds>
                <k_c>1.24518</k_c>
                <k_b>1.60677</k_b>
                <k_uds_err>0.012765</k_uds_err>
                <k_c_err>0.0491882</k_c_err>
                <k_b_err>0.108676</k_b_err>
                <sigma_uds_true>0</sigma_uds_true>
                <sigma_c_true>1426.73</sigma_c_true>
                <sigma_b_true>68.1604</sigma_b_true>
                <sigma_uds>0</sigma_uds>
                <sigma_c>5921.79</sigma_c>
                <sigma_b>365.061</sigma_b>
                <sigma_uds_err>0</sigma_uds_err>
                <sigma_c_err>233.927</sigma_c_err>
                <sigma_b_err>24.6913</sigma_b_err>
        </bin>
        <bin id="9">
                <subbin>
                        <variable>etajet</variable>
                        <low_edge>0.7</low_edge>
                        <up_edge>1.0</up_edge>
                </subbin>
                <k_uds>0.949777</k_uds>
                <k_c>1.37921</k_c>
                <k_b>1.46611</k_b>
                <k_uds_err>0.0144987</k_uds_err>
                <k_c_err>0.0593506</k_c_err>
                <k_b_err>0.122838</k_b_err>
                <sigma_uds_true>0</sigma_uds_true>
                <sigma_c_true>1294.92</sigma_c_true>
                <sigma_b_true>70.627</sigma_b_true>
                <sigma_uds>0</sigma_uds>
                <sigma_c>5953.24</sigma_c>
                <sigma_b>345.157</sigma_b>
                <sigma_uds_err>0</sigma_uds_err>
                <sigma_c_err>256.181</sigma_c_err>
                <sigma_b_err>28.919</sigma_b_err>
        </bin>
        <bin id="10">
                <subbin>
                        <variable>etajet</variable>
                        <low_edge>1.0</low_edge>
                        <up_edge>1.3</up_edge>
                </subbin>
                <k_uds>0.914009</k_uds>
                <k_c>1.36269</k_c>
                <k_b>1.60605</k_b>
                <k_uds_err>0.0171496</k_uds_err>
                <k_c_err>0.0757078</k_c_err>
                <k_b_err>0.162259</k_b_err>
                <sigma_uds_true>0</sigma_uds_true>
                <sigma_c_true>1142.97</sigma_c_true>
                <sigma_b_true>66.7672</sigma_b_true>
                <sigma_uds>0</sigma_uds>
                <sigma_c>5191.72</sigma_c>
                <sigma_b>357.438</sigma_b>
                <sigma_uds_err>0</sigma_uds_err>
                <sigma_c_err>288.439</sigma_c_err>
                <sigma_b_err>36.1118</sigma_b_err>
        </bin>
        <bin id="11">
                <subbin>
                        <variable>etajet</variable>
                        <low_edge>1.3</low_edge>
                        <up_edge>1.6</up_edge>
                </subbin>
                <k_uds>0.809804</k_uds>
                <k_c>1.40921</k_c>
                <k_b>1.41422</k_b>
                <k_uds_err>0.0240125</k_uds_err>
                <k_c_err>0.117522</k_c_err>
                <k_b_err>0.250621</k_b_err>
                <sigma_uds_true>0</sigma_uds_true>
                <sigma_c_true>994.767</sigma_c_true>
                <sigma_b_true>59.2686</sigma_b_true>
                <sigma_uds>0</sigma_uds>
                <sigma_c>4672.77</sigma_c>
                <sigma_b>279.396</sigma_b>
                <sigma_uds_err>0</sigma_uds_err>
                <sigma_c_err>389.691</sigma_c_err>
                <sigma_b_err>49.5132</sigma_b_err>
        </bin>
        <bin id="12">
                <subbin>
                        <variable>etajet</variable>
                        <low_edge>1.6</low_edge>
                        <up_edge>2.2</up_edge>
                </subbin>
                <k_uds>0.658315</k_uds>
                <k_c>1.7043</k_c>
                <k_b>1.52271</k_b>
                <k_uds_err>0.0357726</k_uds_err>
                <k_c_err>0.207133</k_c_err>
                <k_b_err>0.462952</k_b_err>
                <sigma_uds_true>0</sigma_uds_true>
                <sigma_c_true>1569.87</sigma_c_true>
                <sigma_b_true>93.8556</sigma_b_true>
                <sigma_uds>0</sigma_uds>
                <sigma_c>4459.23</sigma_c>
                <sigma_b>238.191</sigma_b>
                <sigma_uds_err>0</sigma_uds_err>
                <sigma_c_err>541.954</sigma_c_err>
                <sigma_b_err>72.4178</sigma_b_err>
        </bin>
        </bin_group>
        <!-- et jet -->
        <bin id="13" type="inlcusive">
                <subbin>
                        <variable>etjet</variable>
                        <low_edge>4.2</low_edge>
                        <up_edge>10000.0</up_edge>
                </subbin>
                <k_uds>0.912311</k_uds>
                <k_c>1.23279</k_c>
                <k_b>1.49805</k_b>
                <k_uds_err>0.00468418</k_uds_err>
                <k_c_err>0.019032</k_c_err>
                <k_b_err>0.051933</k_b_err>
                <sigma_uds_true>0</sigma_uds_true>
                <sigma_c_true>14090.3</sigma_c_true>
                <sigma_b_true>676.917</sigma_b_true>
                <sigma_uds>0</sigma_uds>
                <sigma_c>1.73777</sigma_c>
                <sigma_b>0.101448</sigma_b>
                <sigma_uds_err>0</sigma_uds_err>
                <sigma_c_err>0.026828</sigma_c_err>
                <sigma_b_err>0.00351691</sigma_b_err>
        </bin>
        <bin_group id="etjet">
        <bin id="14">
                <subbin>
                        <variable>etjet</variable>
                        <low_edge>4.2</low_edge>
                        <up_edge>8.0</up_edge>
                </subbin>
                <k_uds>0.932416</k_uds>
                <k_c>1.16122</k_c>
                <k_b>1.60194</k_b>
                <k_uds_err>0.00866719</k_uds_err>
                <k_c_err>0.0377717</k_c_err>
                <k_b_err>0.217436</k_b_err>
                <sigma_uds_true>0</sigma_uds_true>
                <sigma_c_true>11704.5</sigma_c_true>
                <sigma_b_true>414.247</sigma_b_true>
                <sigma_uds>0</sigma_uds>
                <sigma_c>3576.71</sigma_c>
                <sigma_b>174.631</sigma_b>
                <sigma_uds_err>0</sigma_uds_err>
                <sigma_c_err>116.342</sigma_c_err>
                <sigma_b_err>23.7032</sigma_b_err>
        </bin>
        <bin id="15">
                <subbin>
                        <variable>etjet</variable>
                        <low_edge>8.0</low_edge>
                        <up_edge>11.0</up_edge>
                </subbin>
                <k_uds>0.889207</k_uds>
                <k_c>1.32352</k_c>
                <k_b>1.40187</k_b>
                <k_uds_err>0.00938981</k_uds_err>
                <k_c_err>0.0394672</k_c_err>
                <k_b_err>0.0973658</k_b_err>
                <sigma_uds_true>0</sigma_uds_true>
                <sigma_c_true>1623.48</sigma_c_true>
                <sigma_b_true>162.812</sigma_b_true>
                <sigma_uds>0</sigma_uds>
                <sigma_c>716.239</sigma_c>
                <sigma_b>76.0804</sigma_b>
                <sigma_uds_err>0</sigma_uds_err>
                <sigma_c_err>21.3581</sigma_c_err>
                <sigma_b_err>5.28411</sigma_b_err>
        </bin>
        <bin id="16">
                <subbin>
                        <variable>etjet</variable>
                        <low_edge>11.0</low_edge>
                        <up_edge>14.0</up_edge>
                </subbin>
                <k_uds>0.883717</k_uds>
                <k_c>1.34665</k_c>
                <k_b>1.44741</k_b>
                <k_uds_err>0.0138111</k_uds_err>
                <k_c_err>0.0621373</k_c_err>
                <k_b_err>0.0867213</k_b_err>
                <sigma_uds_true>0</sigma_uds_true>
                <sigma_c_true>467.729</sigma_c_true>
                <sigma_b_true>60.5849</sigma_b_true>
                <sigma_uds>0</sigma_uds>
                <sigma_c>209.956</sigma_c>
                <sigma_b>29.2305</sigma_b>
                <sigma_uds_err>0</sigma_uds_err>
                <sigma_c_err>9.68781</sigma_c_err>
                <sigma_b_err>1.75133</sigma_b_err>
        </bin>
        <bin id="17">
                <subbin>
                        <variable>etjet</variable>
                        <low_edge>14.0</low_edge>
                        <up_edge>17.0</up_edge>
                </subbin>
                <k_uds>0.864586</k_uds>
                <k_c>1.44513</k_c>
                <k_b>1.42639</k_b>
                <k_uds_err>0.0208598</k_uds_err>
                <k_c_err>0.10182</k_c_err>
                <k_b_err>0.0993043</k_b_err>
                <sigma_uds_true>0</sigma_uds_true>
                <sigma_c_true>168.232</sigma_c_true>
                <sigma_b_true>23.7725</sigma_b_true>
                <sigma_uds>0</sigma_uds>
                <sigma_c>81.039</sigma_c>
                <sigma_b>11.303</sigma_b>
                <sigma_uds_err>0</sigma_uds_err>
                <sigma_c_err>5.7098</sigma_c_err>
                <sigma_b_err>0.786904</sigma_b_err>
        </bin>
        <bin id="18">
                <subbin>
                        <variable>etjet</variable>
                        <low_edge>17.0</low_edge>
                        <up_edge>20.0</up_edge>
                </subbin>
                <k_uds>0.865813</k_uds>
                <k_c>1.47534</k_c>
                <k_b>1.36343</k_b>
                <k_uds_err>0.0298947</k_uds_err>
                <k_c_err>0.16446</k_c_err>
                <k_b_err>0.145555</k_b_err>
                <sigma_uds_true>0</sigma_uds_true>
                <sigma_c_true>68.9219</sigma_c_true>
                <sigma_b_true>9.78113</sigma_b_true>
                <sigma_uds>0</sigma_uds>
                <sigma_c>33.8944</sigma_c>
                <sigma_b>4.44531</sigma_b>
                <sigma_uds_err>0</sigma_uds_err>
                <sigma_c_err>3.7783</sigma_c_err>
                <sigma_b_err>0.474563</sigma_b_err>
        </bin>
        <bin id="19">
                <subbin>
                        <variable>etjet</variable>
                        <low_edge>20.0</low_edge>
                        <up_edge>25.0</up_edge>
                </subbin>
                <k_uds>0.884291</k_uds>
                <k_c>1.36347</k_c>
                <k_b>1.64338</k_b>
                <k_uds_err>0.0451297</k_uds_err>
                <k_c_err>0.289382</k_c_err>
                <k_b_err>0.212466</k_b_err>
                <sigma_uds_true>0</sigma_uds_true>
                <sigma_c_true>41.1634</sigma_c_true>
                <sigma_b_true>5.70475</sigma_b_true>
                <sigma_uds>0</sigma_uds>
                <sigma_c>11.2251</sigma_c>
                <sigma_b>1.87502</sigma_b>
                <sigma_uds_err>0</sigma_uds_err>
                <sigma_c_err>2.38239</sigma_c_err>
                <sigma_b_err>0.242414</sigma_b_err>
        </bin>
        <bin id="20">
                <subbin>
                        <variable>etjet</variable>
                        <low_edge>25.0</low_edge>
                        <up_edge>35.0</up_edge>
                </subbin>
                <k_uds>0.909552</k_uds>
                <k_c>1.19673</k_c>
                <k_b>1.67875</k_b>
                <k_uds_err>0.0969637</k_uds_err>
                <k_c_err>0.751564</k_c_err>
                <k_b_err>0.421155</k_b_err>
                <sigma_uds_true>0</sigma_uds_true>
                <sigma_c_true>13.2667</sigma_c_true>
                <sigma_b_true>2.03266</sigma_b_true>
                <sigma_uds>0</sigma_uds>
                <sigma_c>1.58766</sigma_c>
                <sigma_b>0.341233</sigma_b>
                <sigma_uds_err>0</sigma_uds_err>
                <sigma_c_err>0.997075</sigma_c_err>
                <sigma_b_err>0.0856065</sigma_b_err>
        </bin>
        </bin_group>
        <!-- phi jet -->
        <bin id="21" type="inlcusive">
                <subbin>
                        <variable>phijet</variable>
                        <low_edge>0</low_edge>
                        <up_edge>6.283</up_edge>
                </subbin>
                <k_uds>0.912297</k_uds>
                <k_c>1.23284</k_c>
                <k_b>1.49796</k_b>
                <k_uds_err>0.00468412</k_uds_err>
                <k_c_err>0.0190318</k_c_err>
                <k_b_err>0.0519337</k_b_err>
                <sigma_uds_true>0</sigma_uds_true>
                <sigma_c_true>14089.9</sigma_c_true>
                <sigma_b_true>676.898</sigma_b_true>
                <sigma_uds>0</sigma_uds>
                <sigma_c>2764.71</sigma_c>
                <sigma_b>161.382</sigma_b>
                <sigma_uds_err>0</sigma_uds_err>
                <sigma_c_err>42.6796</sigma_c_err>
                <sigma_b_err>5.59507</sigma_b_err>
        </bin>
        <bin_group id="phijet">
        <bin id="22">
                <subbin>
                        <variable>phijet</variable>
                        <low_edge>0</low_edge>
                        <up_edge>0.785398</up_edge>
                </subbin>
                <k_uds>0.85059</k_uds>
                <k_c>1.32521</k_c>
                <k_b>1.19031</k_b>
                <k_uds_err>0.0137065</k_uds_err>
                <k_c_err>0.0570958</k_c_err>
                <k_b_err>0.155615</k_b_err>
                <sigma_uds_true>0</sigma_uds_true>
                <sigma_c_true>1759.6</sigma_c_true>
                <sigma_b_true>84.7492</sigma_b_true>
                <sigma_uds>0</sigma_uds>
                <sigma_c>2968.98</sigma_c>
                <sigma_b>128.442</sigma_b>
                <sigma_uds_err>0</sigma_uds_err>
                <sigma_c_err>127.917</sigma_c_err>
                <sigma_b_err>16.7918</sigma_b_err>
        </bin>
        <bin id="23">
                <subbin>
                        <variable>phijet</variable>
                        <low_edge>0.785398</low_edge>
                        <up_edge>1.5708</up_edge>
                </subbin>
                <k_uds>0.944755</k_uds>
                <k_c>1.1871</k_c>
                <k_b>1.43389</k_b>
                <k_uds_err>0.01135</k_uds_err>
                <k_c_err>0.0474674</k_c_err>
                <k_b_err>0.156145</k_b_err>
                <sigma_uds_true>0</sigma_uds_true>
                <sigma_c_true>1759.85</sigma_c_true>
                <sigma_b_true>84.9495</sigma_b_true>
                <sigma_uds>0</sigma_uds>
                <sigma_c>2659.95</sigma_c>
                <sigma_b>155.09</sigma_b>
                <sigma_uds_err>0</sigma_uds_err>
                <sigma_c_err>106.36</sigma_c_err>
                <sigma_b_err>16.8887</sigma_b_err>
        </bin>
        <bin id="24">
                <subbin>
                        <variable>phijet</variable>
                        <low_edge>1.5708</low_edge>
                        <up_edge>2.35619</up_edge>
                </subbin>
                <k_uds>0.902571</k_uds>
                <k_c>1.29792</k_c>
                <k_b>1.24661</k_b>
                <k_uds_err>0.0106454</k_uds_err>
                <k_c_err>0.0434732</k_c_err>
                <k_b_err>0.127755</k_b_err>
                <sigma_uds_true>0</sigma_uds_true>
                <sigma_c_true>1759.65</sigma_c_true>
                <sigma_b_true>84.7413</sigma_b_true>
                <sigma_uds>0</sigma_uds>
                <sigma_c>2907.96</sigma_c>
                <sigma_b>134.506</sigma_b>
                <sigma_uds_err>0</sigma_uds_err>
                <sigma_c_err>97.4006</sigma_c_err>
                <sigma_b_err>13.7844</sigma_b_err>
        </bin>
        <bin id="25">
                <subbin>
                        <variable>phijet</variable>
                        <low_edge>2.35619</low_edge>
                        <up_edge>3.14159</up_edge>
                </subbin>
                <k_uds>0.942812</k_uds>
                <k_c>1.21477</k_c>
                <k_b>1.55863</k_b>
                <k_uds_err>0.0210723</k_uds_err>
                <k_c_err>0.0814026</k_c_err>
                <k_b_err>0.172021</k_b_err>
                <sigma_uds_true>0</sigma_uds_true>
                <sigma_c_true>1765.07</sigma_c_true>
                <sigma_b_true>85.144</sigma_b_true>
                <sigma_uds>0</sigma_uds>
                <sigma_c>2730.02</sigma_c>
                <sigma_b>168.969</sigma_b>
                <sigma_uds_err>0</sigma_uds_err>
                <sigma_c_err>182.94</sigma_c_err>
                <sigma_b_err>18.6485</sigma_b_err>
        </bin>
        <bin id="26">
                <subbin>
                        <variable>phijet</variable>
                        <low_edge>3.14159</low_edge>
                        <up_edge>3.92699</up_edge>
                </subbin>
                <k_uds>0.912296</k_uds>
                <k_c>1.16196</k_c>
                <k_b>1.69146</k_b>
                <k_uds_err>0.0292886</k_uds_err>
                <k_c_err>0.113177</k_c_err>
                <k_b_err>0.206415</k_b_err>
                <sigma_uds_true>0</sigma_uds_true>
                <sigma_c_true>1761.72</sigma_c_true>
                <sigma_b_true>84.7645</sigma_b_true>
                <sigma_uds>0</sigma_uds>
                <sigma_c>2606.38</sigma_c>
                <sigma_b>182.551</sigma_b>
                <sigma_uds_err>0</sigma_uds_err>
                <sigma_c_err>253.866</sigma_c_err>
                <sigma_b_err>22.2775</sigma_b_err>
        </bin>
        <bin id="27">
                <subbin>
                        <variable>phijet</variable>
                        <low_edge>3.92699</low_edge>
                        <up_edge>4.71239</up_edge>
                </subbin>
                <k_uds>0.933561</k_uds>
                <k_c>1.17026</k_c>
                <k_b>1.54801</k_b>
                <k_uds_err>0.0130091</k_uds_err>
                <k_c_err>0.0521362</k_c_err>
                <k_b_err>0.136366</k_b_err>
                <sigma_uds_true>0</sigma_uds_true>
                <sigma_c_true>1764.15</sigma_c_true>
                <sigma_b_true>85.0283</sigma_b_true>
                <sigma_uds>0</sigma_uds>
                <sigma_c>2628.63</sigma_c>
                <sigma_b>167.59</sigma_b>
                <sigma_uds_err>0</sigma_uds_err>
                <sigma_c_err>117.107</sigma_c_err>
                <sigma_b_err>14.7632</sigma_b_err>
        </bin>
        <bin id="28">
                <subbin>
                        <variable>phijet</variable>
                        <low_edge>4.71239</low_edge>
                        <up_edge>5.49779</up_edge>
                </subbin>
                <k_uds>0.918093</k_uds>
                <k_c>1.26206</k_c>
                <k_b>1.61984</k_b>
                <k_uds_err>0.0095949</k_uds_err>
                <k_c_err>0.0395519</k_c_err>
                <k_b_err>0.118531</k_b_err>
                <sigma_uds_true>0</sigma_uds_true>
                <sigma_c_true>1760.08</sigma_c_true>
                <sigma_b_true>84.7567</sigma_b_true>
                <sigma_uds>0</sigma_uds>
                <sigma_c>2828.26</sigma_c>
                <sigma_b>174.806</sigma_b>
                <sigma_uds_err>0</sigma_uds_err>
                <sigma_c_err>88.6355</sigma_c_err>
                <sigma_b_err>12.7913</sigma_b_err>
        </bin>
        <bin id="29">
                <subbin>
                        <variable>phijet</variable>
                        <low_edge>5.49779</low_edge>
                        <up_edge>6.28319</up_edge>
                </subbin>
                <k_uds>0.903002</k_uds>
                <k_c>1.19293</k_c>
                <k_b>1.65124</k_b>
                <k_uds_err>0.0130108</k_uds_err>
                <k_c_err>0.0530484</k_c_err>
                <k_b_err>0.137691</k_b_err>
                <sigma_uds_true>0</sigma_uds_true>
                <sigma_c_true>1758.72</sigma_c_true>
                <sigma_b_true>84.8322</sigma_b_true>
                <sigma_uds>0</sigma_uds>
                <sigma_c>2671.28</sigma_c>
                <sigma_b>178.353</sigma_b>
                <sigma_uds_err>0</sigma_uds_err>
                <sigma_c_err>118.789</sigma_c_err>
                <sigma_b_err>14.8722</sigma_b_err>
        </bin>
        </bin_group>
        <!-- xda -->
        <bin id="30" type="inlcusive">
                <subbin>
                        <variable>xda</variable>
                        <low_edge>0</low_edge>
                        <up_edge>1</up_edge>
                </subbin>
                <k_uds>0.912311</k_uds>
                <k_c>1.23279</k_c>
                <k_b>1.49805</k_b>
                <k_uds_err>0.00468418</k_uds_err>
                <k_c_err>0.019032</k_c_err>
                <k_b_err>0.051933</k_b_err>
                <sigma_uds_true>0</sigma_uds_true>
                <sigma_c_true>14090.3</sigma_c_true>
                <sigma_b_true>676.917</sigma_b_true>
                <sigma_uds>0</sigma_uds>
                <sigma_c>17370.4</sigma_c>
                <sigma_b>1014.05</sigma_b>
                <sigma_uds_err>0</sigma_uds_err>
                <sigma_c_err>268.167</sigma_c_err>
                <sigma_b_err>35.1543</sigma_b_err>
        </bin>
        <bin_group id="xda">
        <bin id="31">
                <subbin>
                        <variable>xda</variable>
                        <low_edge>0.00008</low_edge>
                        <up_edge>0.0002</up_edge>
                </subbin>
                <k_uds>0.970715</k_uds>
                <k_c>1.14695</k_c>
                <k_b>1.40881</k_b>
                <k_uds_err>0.0319471</k_uds_err>
                <k_c_err>0.0946164</k_c_err>
                <k_b_err>0.218563</k_b_err>
                <sigma_uds_true>0</sigma_uds_true>
                <sigma_c_true>1191.57</sigma_c_true>
                <sigma_b_true>77.4694</sigma_b_true>
                <sigma_uds>0</sigma_uds>
                <sigma_c>1.1389e+07</sigma_c>
                <sigma_b>909499</sigma_b>
                <sigma_uds_err>0</sigma_uds_err>
                <sigma_c_err>939520</sigma_c_err>
                <sigma_b_err>141099</sigma_b_err>
        </bin>
        <bin id="32">
                <subbin>
                        <variable>xda</variable>
                        <low_edge>0.0002</low_edge>
                        <up_edge>0.0006</up_edge>
                </subbin>
                <k_uds>0.883812</k_uds>
                <k_c>1.13358</k_c>
                <k_b>1.53744</k_b>
                <k_uds_err>0.0131643</k_uds_err>
                <k_c_err>0.0418572</k_c_err>
                <k_b_err>0.102906</k_b_err>
                <sigma_uds_true>0</sigma_uds_true>
                <sigma_c_true>3849.97</sigma_c_true>
                <sigma_b_true>206.006</sigma_b_true>
                <sigma_uds>0</sigma_uds>
                <sigma_c>1.09106e+07</sigma_c>
                <sigma_b>791808</sigma_b>
                <sigma_uds_err>0</sigma_uds_err>
                <sigma_c_err>402872</sigma_c_err>
                <sigma_b_err>52998</sigma_b_err>
        </bin>
        <bin id="33">
                <subbin>
                        <variable>xda</variable>
                        <low_edge>0.0006</low_edge>
                        <up_edge>0.0016</up_edge>
                </subbin>
                <k_uds>0.870859</k_uds>
                <k_c>1.23368</k_c>
                <k_b>1.46241</k_b>
                <k_uds_err>0.00953232</k_uds_err>
                <k_c_err>0.0330383</k_c_err>
                <k_b_err>0.0885166</k_b_err>
                <sigma_uds_true>0</sigma_uds_true>
                <sigma_c_true>4085.96</sigma_c_true>
                <sigma_b_true>186.413</sigma_b_true>
                <sigma_uds>0</sigma_uds>
                <sigma_c>5.04078e+06</sigma_c>
                <sigma_b>272612</sigma_b>
                <sigma_uds_err>0</sigma_uds_err>
                <sigma_c_err>134993</sigma_c_err>
                <sigma_b_err>16500.7</sigma_b_err>
        </bin>
        <bin id="34">
                <subbin>
                        <variable>xda</variable>
                        <low_edge>0.0016</low_edge>
                        <up_edge>0.005</up_edge>
                </subbin>
                <k_uds>0.928071</k_uds>
                <k_c>1.2861</k_c>
                <k_b>1.43406</k_b>
                <k_uds_err>0.00779343</k_uds_err>
                <k_c_err>0.032651</k_c_err>
                <k_b_err>0.0939258</k_b_err>
                <sigma_uds_true>0</sigma_uds_true>
                <sigma_c_true>3258.26</sigma_c_true>
                <sigma_b_true>140.422</sigma_b_true>
                <sigma_uds>0</sigma_uds>
                <sigma_c>1.23248e+06</sigma_c>
                <sigma_b>59227.6</sigma_b>
                <sigma_uds_err>0</sigma_uds_err>
                <sigma_c_err>31289.8</sigma_c_err>
                <sigma_b_err>3879.2</sigma_b_err>
        </bin>
        <bin id="35">
                <subbin>
                        <variable>xda</variable>
                        <low_edge>0.005</low_edge>
                        <up_edge>0.01</up_edge>
                </subbin>
                <k_uds>0.964034</k_uds>
                <k_c>1.20248</k_c>
                <k_b>1.57718</k_b>
                <k_uds_err>0.011394</k_uds_err>
                <k_c_err>0.060621</k_c_err>
                <k_b_err>0.16637</k_b_err>
                <sigma_uds_true>0</sigma_uds_true>
                <sigma_c_true>1026.35</sigma_c_true>
                <sigma_b_true>42.0872</sigma_b_true>
                <sigma_uds>0</sigma_uds>
                <sigma_c>246833</sigma_c>
                <sigma_b>13275.8</sigma_b>
                <sigma_uds_err>0</sigma_uds_err>
                <sigma_c_err>12443.7</sigma_c_err>
                <sigma_b_err>1400.4</sigma_b_err>
        </bin>
        <bin id="36">
                <subbin>
                        <variable>xda</variable>
                        <low_edge>0.01</low_edge>
                        <up_edge>0.1</up_edge>
                </subbin>
                <k_uds>0.918363</k_uds>
                <k_c>1.41568</k_c>
                <k_b>1.48652</k_b>
                <k_uds_err>0.0134946</k_uds_err>
                <k_c_err>0.103169</k_c_err>
                <k_b_err>0.265546</k_b_err>
                <sigma_uds_true>0</sigma_uds_true>
                <sigma_c_true>661.737</sigma_c_true>
                <sigma_b_true>25.2854</sigma_b_true>
                <sigma_uds>0</sigma_uds>
                <sigma_c>10409</sigma_c>
                <sigma_b>417.635</sigma_b>
                <sigma_uds_err>0</sigma_uds_err>
                <sigma_c_err>758.563</sigma_c_err>
                <sigma_b_err>74.6048</sigma_b_err>
        </bin>
        </bin_group>
        <bin id="37">
                <subbin>
                        <variable>q2da</variable>
                        <low_edge>5.0</low_edge>
                        <up_edge>1000.0</up_edge>
                </subbin>
                <k_uds>0.912311</k_uds>
                <k_c>1.23279</k_c>
                <k_b>1.49805</k_b>
                <k_uds_err>0.00468418</k_uds_err>
                <k_c_err>0.019032</k_c_err>
                <k_b_err>0.051933</k_b_err>
                <sigma_uds_true>0</sigma_uds_true>
                <sigma_c_true>14090.3</sigma_c_true>
                <sigma_b_true>676.917</sigma_b_true>
                <sigma_uds>0</sigma_uds>
                <sigma_c>17.4577</sigma_c>
                <sigma_b>1.01915</sigma_b>
                <sigma_uds_err>0</sigma_uds_err>
                <sigma_c_err>0.269515</sigma_c_err>
                <sigma_b_err>0.035331</sigma_b_err>
        </bin>
        <bin_group id="q2da">
        <bin id="38">
                <subbin>
                        <variable>q2da</variable>
                        <low_edge>5.0</low_edge>
                        <up_edge>10.0</up_edge>
                </subbin>
                <k_uds>0.92016</k_uds>
                <k_c>1.16223</k_c>
                <k_b>1.7027</k_b>
                <k_uds_err>0.0133246</k_uds_err>
                <k_c_err>0.0486117</k_c_err>
                <k_b_err>0.148112</k_b_err>
                <sigma_uds_true>0</sigma_uds_true>
                <sigma_c_true>3755.45</sigma_c_true>
                <sigma_b_true>171.543</sigma_b_true>
                <sigma_uds>0</sigma_uds>
                <sigma_c>872.943</sigma_c>
                <sigma_b>58.4173</sigma_b>
                <sigma_uds_err>0</sigma_uds_err>
                <sigma_c_err>36.5118</sigma_c_err>
                <sigma_b_err>5.08152</sigma_b_err>
        </bin>
        <bin id="39">
                <subbin>
                        <variable>q2da</variable>
                        <low_edge>10.0</low_edge>
                        <up_edge>20.0</up_edge>
                </subbin>
                <k_uds>0.893792</k_uds>
                <k_c>1.24445</k_c>
                <k_b>1.47267</k_b>
                <k_uds_err>0.0101847</k_uds_err>
                <k_c_err>0.0400147</k_c_err>
                <k_b_err>0.127367</k_b_err>
                <sigma_uds_true>0</sigma_uds_true>
                <sigma_c_true>3784.34</sigma_c_true>
                <sigma_b_true>160.332</sigma_b_true>
                <sigma_uds>0</sigma_uds>
                <sigma_c>470.943</sigma_c>
                <sigma_b>23.6116</sigma_b>
                <sigma_uds_err>0</sigma_uds_err>
                <sigma_c_err>15.1429</sigma_c_err>
                <sigma_b_err>2.0421</sigma_b_err>
        </bin>
        <bin id="40">
                <subbin>
                        <variable>q2da</variable>
                        <low_edge>20.0</low_edge>
                        <up_edge>40.0</up_edge>
                </subbin>
                <k_uds>0.895793</k_uds>
                <k_c>1.27042</k_c>
                <k_b>1.45346</k_b>
                <k_uds_err>0.00961674</k_uds_err>
                <k_c_err>0.0395479</k_c_err>
                <k_b_err>0.124962</k_b_err>
                <sigma_uds_true>0</sigma_uds_true>
                <sigma_c_true>3191.76</sigma_c_true>
                <sigma_b_true>137.859</sigma_b_true>
                <sigma_uds>0</sigma_uds>
                <sigma_c>202.744</sigma_c>
                <sigma_b>10.0186</sigma_b>
                <sigma_uds_err>0</sigma_uds_err>
                <sigma_c_err>6.31137</sigma_c_err>
                <sigma_b_err>0.861356</sigma_b_err>
        </bin>
        <bin id="41">
                <subbin>
                        <variable>q2da</variable>
                        <low_edge>40.0</low_edge>
                        <up_edge>70.0</up_edge>
                </subbin>
                <k_uds>0.902102</k_uds>
                <k_c>1.21339</k_c>
                <k_b>1.51526</k_b>
                <k_uds_err>0.0112933</k_uds_err>
                <k_c_err>0.0481925</k_c_err>
                <k_b_err>0.139435</k_b_err>
                <sigma_uds_true>0</sigma_uds_true>
                <sigma_c_true>1670.23</sigma_c_true>
                <sigma_b_true>86.6562</sigma_b_true>
                <sigma_uds>0</sigma_uds>
                <sigma_c>67.5543</sigma_c>
                <sigma_b>4.3769</sigma_b>
                <sigma_uds_err>0</sigma_uds_err>
                <sigma_c_err>2.68308</sigma_c_err>
                <sigma_b_err>0.402764</sigma_b_err>
        </bin>
        <bin id="42">
                <subbin>
                        <variable>q2da</variable>
                        <low_edge>70.0</low_edge>
                        <up_edge>120.0</up_edge>
                </subbin>
                <k_uds>0.911164</k_uds>
                <k_c>1.26305</k_c>
                <k_b>1.2263</k_b>
                <k_uds_err>0.0131655</k_uds_err>
                <k_c_err>0.0574637</k_c_err>
                <k_b_err>0.134846</k_b_err>
                <sigma_uds_true>0</sigma_uds_true>
                <sigma_c_true>891.873</sigma_c_true>
                <sigma_b_true>58.3251</sigma_b_true>
                <sigma_uds>0</sigma_uds>
                <sigma_c>22.5295</sigma_c>
                <sigma_b>1.43048</sigma_b>
                <sigma_uds_err>0</sigma_uds_err>
                <sigma_c_err>1.02501</sigma_c_err>
                <sigma_b_err>0.157298</sigma_b_err>
        </bin>
        <bin id="43">
                <subbin>
                        <variable>q2da</variable>
                        <low_edge>120.0</low_edge>
                        <up_edge>200.0</up_edge>
                </subbin>
                <k_uds>0.954012</k_uds>
                <k_c>1.20736</k_c>
                <k_b>1.72403</k_b>
                <k_uds_err>0.0183481</k_uds_err>
                <k_c_err>0.0828778</k_c_err>
                <k_b_err>0.162538</k_b_err>
                <sigma_uds_true>0</sigma_uds_true>
                <sigma_c_true>434.079</sigma_c_true>
                <sigma_b_true>34.0346</sigma_b_true>
                <sigma_uds>0</sigma_uds>
                <sigma_c>6.55111</sigma_c>
                <sigma_b>0.733457</sigma_b>
                <sigma_uds_err>0</sigma_uds_err>
                <sigma_c_err>0.449694</sigma_c_err>
                <sigma_b_err>0.0691489</sigma_b_err>
        </bin>
        <bin id="44">
                <subbin>
                        <variable>q2da</variable>
                        <low_edge>200.0</low_edge>
                        <up_edge>400.0</up_edge>
                </subbin>
                <k_uds>0.983342</k_uds>
                <k_c>1.33804</k_c>
                <k_b>1.46416</k_b>
                <k_uds_err>0.0219276</k_uds_err>
                <k_c_err>0.099789</k_c_err>
                <k_b_err>0.162934</k_b_err>
                <sigma_uds_true>0</sigma_uds_true>
                <sigma_c_true>259.926</sigma_c_true>
                <sigma_b_true>21.8051</sigma_b_true>
                <sigma_uds>0</sigma_uds>
                <sigma_c>1.73895</sigma_c>
                <sigma_b>0.159631</sigma_b>
                <sigma_uds_err>0</sigma_uds_err>
                <sigma_c_err>0.129689</sigma_c_err>
                <sigma_b_err>0.017764</sigma_b_err>
        </bin>
        <bin id="45">
                <subbin>
                        <variable>q2da</variable>
                        <low_edge>400.0</low_edge>
                        <up_edge>1000.0</up_edge>
                </subbin>
                <k_uds>1.11933</k_uds>
                <k_c>1.11633</k_c>
                <k_b>1.28401</k_b>
                <k_uds_err>0.0381646</k_uds_err>
                <k_c_err>0.176464</k_c_err>
                <k_b_err>0.253428</k_b_err>
                <sigma_uds_true>0</sigma_uds_true>
                <sigma_c_true>102.692</sigma_c_true>
                <sigma_b_true>8.1319</sigma_b_true>
                <sigma_uds>0</sigma_uds>
                <sigma_c>0.191063</sigma_c>
                <sigma_b>0.0174023</sigma_b>
                <sigma_uds_err>0</sigma_uds_err>
                <sigma_c_err>0.0302022</sigma_c_err>
                <sigma_b_err>0.00343474</sigma_b_err>
        </bin>
        </bin_group>
        <bin_group id="q2da_xda_bin1">
        <bin id="46">
                <subbin>
                        <variable>q2da</variable>
                        <low_edge>5.0</low_edge>
                        <up_edge>20.0</up_edge>
                </subbin>
                <subbin>
                        <variable>xda</variable>
                        <low_edge>0.00008</low_edge>
                        <up_edge>0.0002</up_edge>
                </subbin>
                <k_uds>0.970715</k_uds>
                <k_c>1.14695</k_c>
                <k_b>1.40881</k_b>
                <k_uds_err>0.0319471</k_uds_err>
                <k_c_err>0.0946164</k_c_err>
                <k_b_err>0.218563</k_b_err>
                <sigma_uds_true>0</sigma_uds_true>
                <sigma_c_true>1191.57</sigma_c_true>
                <sigma_b_true>77.4694</sigma_b_true>
                <sigma_uds>0</sigma_uds>
                <sigma_c>1.1389e+07</sigma_c>
                <sigma_b>909499</sigma_b>
                <sigma_uds_err>0</sigma_uds_err>
                <sigma_c_err>939520</sigma_c_err>
                <sigma_b_err>141099</sigma_b_err>
        </bin>
        <bin id="47">
                <subbin>
                        <variable>q2da</variable>
                        <low_edge>5.0</low_edge>
                        <up_edge>20.0</up_edge>
                </subbin>
                <subbin>
                        <variable>xda</variable>
                        <low_edge>0.0002</low_edge>
                        <up_edge>0.0003</up_edge>
                </subbin>
                <k_uds>0.888604</k_uds>
                <k_c>1.27394</k_c>
                <k_b>1.28202</k_b>
                <k_uds_err>0.0277274</k_uds_err>
                <k_c_err>0.084241</k_c_err>
                <k_b_err>0.195608</k_b_err>
                <sigma_uds_true>0</sigma_uds_true>
                <sigma_c_true>1153.89</sigma_c_true>
                <sigma_b_true>67.8189</sigma_b_true>
                <sigma_uds>0</sigma_uds>
                <sigma_c>1.46999e+07</sigma_c>
                <sigma_b>869454</sigma_b>
                <sigma_uds_err>0</sigma_uds_err>
                <sigma_c_err>972052</sigma_c_err>
                <sigma_b_err>132659</sigma_b_err>
        </bin>
        <bin id="48">
                <subbin>
                        <variable>q2da</variable>
                        <low_edge>5.0</low_edge>
                        <up_edge>20.0</up_edge>
                </subbin>
                <subbin>
                        <variable>xda</variable>
                        <low_edge>0.0003</low_edge>
                        <up_edge>0.0005</up_edge>
                </subbin>
                <k_uds>0.890618</k_uds>
                <k_c>1.07009</k_c>
                <k_b>1.68097</k_b>
                <k_uds_err>0.0188135</k_uds_err>
                <k_c_err>0.061968</k_c_err>
                <k_b_err>0.162611</k_b_err>
                <sigma_uds_true>0</sigma_uds_true>
                <sigma_c_true>1657.14</sigma_c_true>
                <sigma_b_true>81.0236</sigma_b_true>
                <sigma_uds>0</sigma_uds>
                <sigma_c>8.8665e+06</sigma_c>
                <sigma_b>680991</sigma_b>
                <sigma_uds_err>0</sigma_uds_err>
                <sigma_c_err>513449</sigma_c_err>
                <sigma_b_err>65876.5</sigma_b_err>
        </bin>
        <bin id="49">
                <subbin>
                        <variable>q2da</variable>
                        <low_edge>5.0</low_edge>
                        <up_edge>20.0</up_edge>
                </subbin>
                <subbin>
                        <variable>xda</variable>
                        <low_edge>0.0005</low_edge>
                        <up_edge>0.003</up_edge>
                </subbin>
                <k_uds>0.893467</k_uds>
                <k_c>1.2383</k_c>
                <k_b>1.61176</k_b>
                <k_uds_err>0.0104098</k_uds_err>
                <k_c_err>0.0428881</k_c_err>
                <k_b_err>0.167179</k_b_err>
                <sigma_uds_true>0</sigma_uds_true>
                <sigma_c_true>3278.8</sigma_c_true>
                <sigma_b_true>102.981</sigma_b_true>
                <sigma_uds>0</sigma_uds>
                <sigma_c>1.62405e+06</sigma_c>
                <sigma_b>66392.4</sigma_b>
                <sigma_uds_err>0</sigma_uds_err>
                <sigma_c_err>56248.6</sigma_c_err>
                <sigma_b_err>6886.52</sigma_b_err>
        </bin>
        </bin_group>
        <bin_group id="q2da_xda_bin2">
        <bin id="50">
                <subbin>
                        <variable>q2da</variable>
                        <low_edge>20.0</low_edge>
                        <up_edge>60.0</up_edge>
                </subbin>
                <subbin>
                        <variable>xda</variable>
                        <low_edge>0.0003</low_edge>
                        <up_edge>0.0005</up_edge>
                </subbin>
                <k_uds>0.860851</k_uds>
                <k_c>1.09632</k_c>
                <k_b>1.38223</k_b>
                <k_uds_err>0.06617</k_uds_err>
                <k_c_err>0.17584</k_c_err>
                <k_b_err>0.30023</k_b_err>
                <sigma_uds_true>0</sigma_uds_true>
                <sigma_c_true>268.056</sigma_c_true>
                <sigma_b_true>19.7837</sigma_b_true>
                <sigma_uds>0</sigma_uds>
                <sigma_c>1.46938e+06</sigma_c>
                <sigma_b>136728</sigma_b>
                <sigma_uds_err>0</sigma_uds_err>
                <sigma_c_err>235675</sigma_c_err>
                <sigma_b_err>29698.2</sigma_b_err>
        </bin>
        <bin id="51">
                <subbin>
                        <variable>q2da</variable>
                        <low_edge>20.0</low_edge>
                        <up_edge>60.0</up_edge>
                </subbin>
                <subbin>
                        <variable>xda</variable>
                        <low_edge>0.0005</low_edge>
                        <up_edge>0.0012</up_edge>
                </subbin>
                <k_uds>0.834421</k_uds>
                <k_c>1.3013</k_c>
                <k_b>1.31412</k_b>
                <k_uds_err>0.0185813</k_uds_err>
                <k_c_err>0.0547983</k_c_err>
                <k_b_err>0.114723</k_b_err>
                <sigma_uds_true>0</sigma_uds_true>
                <sigma_c_true>1430.55</sigma_c_true>
                <sigma_b_true>88.05</sigma_b_true>
                <sigma_uds>0</sigma_uds>
                <sigma_c>2.65939e+06</sigma_c>
                <sigma_b>165297</sigma_b>
                <sigma_uds_err>0</sigma_uds_err>
                <sigma_c_err>111988</sigma_c_err>
                <sigma_b_err>14430.5</sigma_b_err>
        </bin>
        <bin id="52">
                <subbin>
                        <variable>q2da</variable>
                        <low_edge>20.0</low_edge>
                        <up_edge>60.0</up_edge>
                </subbin>
                <subbin>
                        <variable>xda</variable>
                        <low_edge>0.0012</low_edge>
                        <up_edge>0.002</up_edge>
                </subbin>
                <k_uds>0.913639</k_uds>
                <k_c>1.19801</k_c>
                <k_b>1.41372</k_b>
                <k_uds_err>0.0167967</k_uds_err>
                <k_c_err>0.0591975</k_c_err>
                <k_b_err>0.162079</k_b_err>
                <sigma_uds_true>0</sigma_uds_true>
                <sigma_c_true>939.111</sigma_c_true>
                <sigma_b_true>44.9172</sigma_b_true>
                <sigma_uds>0</sigma_uds>
                <sigma_c>1.40633e+06</sigma_c>
                <sigma_b>79375.6</sigma_b>
                <sigma_uds_err>0</sigma_uds_err>
                <sigma_c_err>69491.3</sigma_c_err>
                <sigma_b_err>9100.16</sigma_b_err>
        </bin>
        <bin id="53">
                <subbin>
                        <variable>q2da</variable>
                        <low_edge>20.0</low_edge>
                        <up_edge>60.0</up_edge>
                </subbin>
                <subbin>
                        <variable>xda</variable>
                        <low_edge>0.002</low_edge>
                        <up_edge>0.0035</up_edge>
                </subbin>
                <k_uds>0.933725</k_uds>
                <k_c>1.17782</k_c>
                <k_b>1.62686</k_b>
                <k_uds_err>0.0145102</k_uds_err>
                <k_c_err>0.0600651</k_c_err>
                <k_b_err>0.23333</k_b_err>
                <sigma_uds_true>0</sigma_uds_true>
                <sigma_c_true>827.998</sigma_c_true>
                <sigma_b_true>30.8566</sigma_b_true>
                <sigma_uds>0</sigma_uds>
                <sigma_c>650154</sigma_c>
                <sigma_b>33466.3</sigma_b>
                <sigma_uds_err>0</sigma_uds_err>
                <sigma_c_err>33155.8</sigma_c_err>
                <sigma_b_err>4799.85</sigma_b_err>
        </bin>
        <bin id="54">
                <subbin>
                        <variable>q2da</variable>
                        <low_edge>20.0</low_edge>
                        <up_edge>60.0</up_edge>
                </subbin>
                <subbin>
                        <variable>xda</variable>
                        <low_edge>0.0035</low_edge>
                        <up_edge>0.01</up_edge>
                </subbin>
                <k_uds>0.92819</k_uds>
                <k_c>1.36284</k_c>
                <k_b>1.33708</k_b>
                <k_uds_err>0.015638</k_uds_err>
                <k_c_err>0.0999771</k_c_err>
                <k_b_err>0.713219</k_b_err>
                <sigma_uds_true>0</sigma_uds_true>
                <sigma_c_true>861.551</sigma_c_true>
                <sigma_b_true>18.6667</sigma_b_true>
                <sigma_uds>0</sigma_uds>
                <sigma_c>180639</sigma_c>
                <sigma_b>3839.82</sigma_b>
                <sigma_uds_err>0</sigma_uds_err>
                <sigma_c_err>13251.6</sigma_c_err>
                <sigma_b_err>2048.22</sigma_b_err>
        </bin>
        </bin_group>
        <bin_group id="q2da_xda_bin3">
        <bin id="55">
                <subbin>
                        <variable>q2da</variable>
                        <low_edge>60.0</low_edge>
                        <up_edge>120.0</up_edge>
                </subbin>
                <subbin>
                        <variable>xda</variable>
                        <low_edge>0.0008</low_edge>
                        <up_edge>0.0018</up_edge>
                </subbin>
                <k_uds>0.900135</k_uds>
                <k_c>1.08297</k_c>
                <k_b>1.64597</k_b>
                <k_uds_err>0.0450054</k_uds_err>
                <k_c_err>0.132007</k_c_err>
                <k_b_err>0.196276</k_b_err>
                <sigma_uds_true>0</sigma_uds_true>
                <sigma_c_true>250.226</sigma_c_true>
                <sigma_b_true>21.8176</sigma_b_true>
                <sigma_uds>0</sigma_uds>
                <sigma_c>270987</sigma_c>
                <sigma_b>35911</sigma_b>
                <sigma_uds_err>0</sigma_uds_err>
                <sigma_c_err>33031.5</sigma_c_err>
                <sigma_b_err>4282.27</sigma_b_err>
        </bin>
        <bin id="56">
                <subbin>
                        <variable>q2da</variable>
                        <low_edge>60.0</low_edge>
                        <up_edge>120.0</up_edge>
                </subbin>
                <subbin>
                        <variable>xda</variable>
                        <low_edge>0.0018</low_edge>
                        <up_edge>0.003</up_edge>
                </subbin>
                <k_uds>0.925985</k_uds>
                <k_c>1.15685</k_c>
                <k_b>1.40549</k_b>
                <k_uds_err>0.0270613</k_uds_err>
                <k_c_err>0.090541</k_c_err>
                <k_b_err>0.16935</k_b_err>
                <sigma_uds_true>0</sigma_uds_true>
                <sigma_c_true>304.881</sigma_c_true>
                <sigma_b_true>23.0741</sigma_b_true>
                <sigma_uds>0</sigma_uds>
                <sigma_c>293917</sigma_c>
                <sigma_b>27025.4</sigma_b>
                <sigma_uds_err>0</sigma_uds_err>
                <sigma_c_err>23003.5</sigma_c_err>
                <sigma_b_err>3256.33</sigma_b_err>
        </bin>
        <bin id="57">
                <subbin>
                        <variable>q2da</variable>
                        <low_edge>60.0</low_edge>
                        <up_edge>120.0</up_edge>
                </subbin>
                <subbin>
                        <variable>xda</variable>
                        <low_edge>0.003</low_edge>
                        <up_edge>0.006</up_edge>
                </subbin>
                <k_uds>0.944676</k_uds>
                <k_c>1.21827</k_c>
                <k_b>1.20036</k_b>
                <k_uds_err>0.0190905</k_uds_err>
                <k_c_err>0.0745718</k_c_err>
                <k_b_err>0.19351</k_b_err>
                <sigma_uds_true>0</sigma_uds_true>
                <sigma_c_true>339.891</sigma_c_true>
                <sigma_b_true>21.3821</sigma_b_true>
                <sigma_uds>0</sigma_uds>
                <sigma_c>138026</sigma_c>
                <sigma_b>8555.41</sigma_b>
                <sigma_uds_err>0</sigma_uds_err>
                <sigma_c_err>8448.75</sigma_c_err>
                <sigma_b_err>1379.22</sigma_b_err>
        </bin>
        <bin id="58">
                <subbin>
                        <variable>q2da</variable>
                        <low_edge>60.0</low_edge>
                        <up_edge>120.0</up_edge>
                </subbin>
                <subbin>
                        <variable>xda</variable>
                        <low_edge>0.006</low_edge>
                        <up_edge>0.04</up_edge>
                </subbin>
                <k_uds>0.879794</k_uds>
                <k_c>1.48989</k_c>
                <k_b>0.463487</k_b>
                <k_uds_err>0.0183322</k_uds_err>
                <k_c_err>0.122345</k_c_err>
                <k_b_err>0.546533</k_b_err>
                <sigma_uds_true>0</sigma_uds_true>
                <sigma_c_true>370.155</sigma_c_true>
                <sigma_b_true>13.2689</sigma_b_true>
                <sigma_uds>0</sigma_uds>
                <sigma_c>16220.3</sigma_c>
                <sigma_b>180.881</sigma_b>
                <sigma_uds_err>0</sigma_uds_err>
                <sigma_c_err>1331.95</sigma_c_err>
                <sigma_b_err>213.291</sigma_b_err>
        </bin>
        </bin_group>
        <bin_group id="q2da_xda_bin4">
        <bin id="59">
                <subbin>
                        <variable>q2da</variable>
                        <low_edge>120.0</low_edge>
                        <up_edge>400.0</up_edge>
                </subbin>
                <subbin>
                        <variable>xda</variable>
                        <low_edge>0.0016</low_edge>
                        <up_edge>0.005</up_edge>
                </subbin>
                <k_uds>0.823694</k_uds>
                <k_c>1.49253</k_c>
                <k_b>1.11085</k_b>
                <k_uds_err>0.0311175</k_uds_err>
                <k_c_err>0.103329</k_c_err>
                <k_b_err>0.145896</k_b_err>
                <sigma_uds_true>0</sigma_uds_true>
                <sigma_c_true>240.688</sigma_c_true>
                <sigma_b_true>23.0955</sigma_b_true>
                <sigma_uds>0</sigma_uds>
                <sigma_c>105657</sigma_c>
                <sigma_b>7545.77</sigma_b>
                <sigma_uds_err>0</sigma_uds_err>
                <sigma_c_err>7314.71</sigma_c_err>
                <sigma_b_err>991.042</sigma_b_err>
        </bin>
        <bin id="60">
                <subbin>
                        <variable>q2da</variable>
                        <low_edge>120.0</low_edge>
                        <up_edge>400.0</up_edge>
                </subbin>
                <subbin>
                        <variable>xda</variable>
                        <low_edge>0.005</low_edge>
                        <up_edge>0.016</up_edge>
                </subbin>
                <k_uds>1.02909</k_uds>
                <k_c>1.10637</k_c>
                <k_b>1.8747</k_b>
                <k_uds_err>0.0187316</k_uds_err>
                <k_c_err>0.0764836</k_c_err>
                <k_b_err>0.145866</k_b_err>
                <sigma_uds_true>0</sigma_uds_true>
                <sigma_c_true>333.989</sigma_c_true>
                <sigma_b_true>27.3551</sigma_b_true>
                <sigma_uds>0</sigma_uds>
                <sigma_c>33592.5</sigma_c>
                <sigma_b>4662.05</sigma_b>
                <sigma_uds_err>0</sigma_uds_err>
                <sigma_c_err>2322.24</sigma_c_err>
                <sigma_b_err>362.744</sigma_b_err>
        </bin>
        <bin id="61">
                <subbin>
                        <variable>q2da</variable>
                        <low_edge>120.0</low_edge>
                        <up_edge>400.0</up_edge>
                </subbin>
                <subbin>
                        <variable>xda</variable>
                        <low_edge>0.016</low_edge>
                        <up_edge>0.06</up_edge>
                </subbin>
                <k_uds>0.944421</k_uds>
                <k_c>1.59776</k_c>
                <k_b>1.53926</k_b>
                <k_uds_err>0.0311897</k_uds_err>
                <k_c_err>0.292665</k_c_err>
                <k_b_err>0.785241</k_b_err>
                <sigma_uds_true>0</sigma_uds_true>
                <sigma_c_true>116.341</sigma_c_true>
                <sigma_b_true>5.31508</sigma_b_true>
                <sigma_uds>0</sigma_uds>
                <sigma_c>4224.64</sigma_c>
                <sigma_b>185.939</sigma_b>
                <sigma_uds_err>0</sigma_uds_err>
                <sigma_c_err>773.836</sigma_c_err>
                <sigma_b_err>94.855</sigma_b_err>
        </bin>
        </bin_group>
        <bin_group id="q2da_xda_bin5">
        <bin id="62">
                <subbin>
                        <variable>q2da</variable>
                        <low_edge>400.0</low_edge>
                        <up_edge>1000.0</up_edge>
                </subbin>
                <subbin>
                        <variable>xda</variable>
                        <low_edge>0.005</low_edge>
                        <up_edge>0.02</up_edge>
                </subbin>
                <k_uds>1.05773</k_uds>
                <k_c>1.13566</k_c>
                <k_b>0.989769</k_b>
                <k_uds_err>0.0528551</k_uds_err>
                <k_c_err>0.178288</k_c_err>
                <k_b_err>0.245885</k_b_err>
                <sigma_uds_true>0</sigma_uds_true>
                <sigma_c_true>64.9826</sigma_c_true>
                <sigma_b_true>5.71794</sigma_b_true>
                <sigma_uds>0</sigma_uds>
                <sigma_c>4919.87</sigma_c>
                <sigma_b>377.296</sigma_b>
                <sigma_uds_err>0</sigma_uds_err>
                <sigma_c_err>772.375</sigma_c_err>
                <sigma_b_err>93.7305</sigma_b_err>
        </bin>
        <bin id="63">
                <subbin>
                        <variable>q2da</variable>
                        <low_edge>400.0</low_edge>
                        <up_edge>1000.0</up_edge>
                </subbin>
                <subbin>
                        <variable>xda</variable>
                        <low_edge>0.02</low_edge>
                        <up_edge>0.1</up_edge>
                </subbin>
                <k_uds>1.18557</k_uds>
                <k_c>1.0736</k_c>
                <k_b>1.83853</k_b>
                <k_uds_err>0.0586466</k_uds_err>
                <k_c_err>0.424556</k_c_err>
                <k_b_err>0.644023</k_b_err>
                <sigma_uds_true>0</sigma_uds_true>
                <sigma_c_true>36.8493</sigma_c_true>
                <sigma_b_true>2.38276</sigma_b_true>
                <sigma_uds>0</sigma_uds>
                <sigma_c>494.515</sigma_c>
                <sigma_b>54.7598</sigma_b>
                <sigma_uds_err>0</sigma_uds_err>
                <sigma_c_err>195.557</sigma_c_err>
                <sigma_b_err>19.1819</sigma_b_err>
        </bin>
        </bin_group>
</binning>