<?xml version="1.0" encoding="UTF-8" standalone="no" ?><!DOCTYPE dataset SYSTEM "binning.dtd"><?xml-stylesheet type="text/xsl" href="binning.xsl"?><binning>
        <!-- eta jet -->
        <bin id="1" type="inlcusive">
                <subbin>
                        <variable>etajet</variable>
                        <low_edge>-1.6</low_edge>
                        <up_edge>2.2</up_edge>
                </subbin>
                <k_uds>0.907631</k_uds>
                <k_c>1.27032</k_c>
                <k_b>1.4668</k_b>
                <k_uds_err>0.00477645</k_uds_err>
                <k_c_err>0.0199508</k_c_err>
                <k_b_err>0.0502009</k_b_err>
                <sigma_uds_true>0</sigma_uds_true>
                <sigma_c_true>9441.9</sigma_c_true>
                <sigma_b_true>599.598</sigma_b_true>
                <sigma_uds>0</sigma_uds>
                <sigma_c>3156.37</sigma_c>
                <sigma_b>231.445</sigma_b>
                <sigma_uds_err>0</sigma_uds_err>
                <sigma_c_err>49.5719</sigma_c_err>
                <sigma_b_err>7.92115</sigma_b_err>
        </bin>
        <bin_group id="etajet">
        <bin id="2">
                <subbin>
                        <variable>etajet</variable>
                        <low_edge>-1.6</low_edge>
                        <up_edge>-0.8</up_edge>
                </subbin>
                <k_uds>0.925273</k_uds>
                <k_c>1.21096</k_c>
                <k_b>1.36328</k_b>
                <k_uds_err>0.0158884</k_uds_err>
                <k_c_err>0.061048</k_c_err>
                <k_b_err>0.386277</k_b_err>
                <sigma_uds_true>0</sigma_uds_true>
                <sigma_c_true>1136.47</sigma_c_true>
                <sigma_b_true>61.5594</sigma_b_true>
                <sigma_uds>0</sigma_uds>
                <sigma_c>1720.27</sigma_c>
                <sigma_b>104.903</sigma_b>
                <sigma_uds_err>0</sigma_uds_err>
                <sigma_c_err>86.7239</sigma_c_err>
                <sigma_b_err>29.7238</sigma_b_err>
        </bin>
        <bin id="3">
                <subbin>
                        <variable>etajet</variable>
                        <low_edge>-0.8</low_edge>
                        <up_edge>-0.5</up_edge>
                </subbin>
                <k_uds>0.97133</k_uds>
                <k_c>1.16063</k_c>
                <k_b>1.48244</k_b>
                <k_uds_err>0.0155465</k_uds_err>
                <k_c_err>0.0538192</k_c_err>
                <k_b_err>0.177612</k_b_err>
                <sigma_uds_true>0</sigma_uds_true>
                <sigma_c_true>836.26</sigma_c_true>
                <sigma_b_true>50.4219</sigma_b_true>
                <sigma_uds>0</sigma_uds>
                <sigma_c>3235.3</sigma_c>
                <sigma_b>249.158</sigma_b>
                <sigma_uds_err>0</sigma_uds_err>
                <sigma_c_err>150.023</sigma_c_err>
                <sigma_b_err>29.8519</sigma_b_err>
        </bin>
        <bin id="4">
                <subbin>
                        <variable>etajet</variable>
                        <low_edge>-0.5</low_edge>
                        <up_edge>-0.2</up_edge>
                </subbin>
                <k_uds>0.946913</k_uds>
                <k_c>1.19509</k_c>
                <k_b>1.23976</k_b>
                <k_uds_err>0.0130676</k_uds_err>
                <k_c_err>0.0455913</k_c_err>
                <k_b_err>0.119319</k_b_err>
                <sigma_uds_true>0</sigma_uds_true>
                <sigma_c_true>994.307</sigma_c_true>
                <sigma_b_true>57.6245</sigma_b_true>
                <sigma_uds>0</sigma_uds>
                <sigma_c>3960.95</sigma_c>
                <sigma_b>238.136</sigma_b>
                <sigma_uds_err>0</sigma_uds_err>
                <sigma_c_err>151.106</sigma_c_err>
                <sigma_b_err>22.9191</sigma_b_err>
        </bin>
        <bin id="5">
                <subbin>
                        <variable>etajet</variable>
                        <low_edge>-0.2</low_edge>
                        <up_edge>0.1</up_edge>
                </subbin>
                <k_uds>0.958469</k_uds>
                <k_c>1.16783</k_c>
                <k_b>1.44652</k_b>
                <k_uds_err>0.0127449</k_uds_err>
                <k_c_err>0.0454331</k_c_err>
                <k_b_err>0.105982</k_b_err>
                <sigma_uds_true>0</sigma_uds_true>
                <sigma_c_true>1073.16</sigma_c_true>
                <sigma_b_true>60.58</sigma_b_true>
                <sigma_uds>0</sigma_uds>
                <sigma_c>4177.55</sigma_c>
                <sigma_b>292.1</sigma_b>
                <sigma_uds_err>0</sigma_uds_err>
                <sigma_c_err>162.523</sigma_c_err>
                <sigma_b_err>21.4013</sigma_b_err>
        </bin>
        <bin id="6">
                <subbin>
                        <variable>etajet</variable>
                        <low_edge>0.1</low_edge>
                        <up_edge>0.4</up_edge>
                </subbin>
                <k_uds>0.954531</k_uds>
                <k_c>1.24852</k_c>
                <k_b>1.41135</k_b>
                <k_uds_err>0.0128244</k_uds_err>
                <k_c_err>0.0476998</k_c_err>
                <k_b_err>0.104287</k_b_err>
                <sigma_uds_true>0</sigma_uds_true>
                <sigma_c_true>1071.57</sigma_c_true>
                <sigma_b_true>63.709</sigma_b_true>
                <sigma_uds>0</sigma_uds>
                <sigma_c>4459.58</sigma_c>
                <sigma_b>299.719</sigma_b>
                <sigma_uds_err>0</sigma_uds_err>
                <sigma_c_err>170.379</sigma_c_err>
                <sigma_b_err>22.1467</sigma_b_err>
        </bin>
        <bin id="7">
                <subbin>
                        <variable>etajet</variable>
                        <low_edge>0.4</low_edge>
                        <up_edge>0.7</up_edge>
                </subbin>
                <k_uds>0.963594</k_uds>
                <k_c>1.28055</k_c>
                <k_b>1.56663</k_b>
                <k_uds_err>0.0128702</k_uds_err>
                <k_c_err>0.0508939</k_c_err>
                <k_b_err>0.10768</k_b_err>
                <sigma_uds_true>0</sigma_uds_true>
                <sigma_c_true>998.266</sigma_c_true>
                <sigma_b_true>65.5907</sigma_b_true>
                <sigma_uds>0</sigma_uds>
                <sigma_c>4261.11</sigma_c>
                <sigma_b>342.521</sigma_b>
                <sigma_uds_err>0</sigma_uds_err>
                <sigma_c_err>169.352</sigma_c_err>
                <sigma_b_err>23.5426</sigma_b_err>
        </bin>
        <bin id="8">
                <subbin>
                        <variable>etajet</variable>
                        <low_edge>0.7</low_edge>
                        <up_edge>1.0</up_edge>
                </subbin>
                <k_uds>0.949961</k_uds>
                <k_c>1.41003</k_c>
                <k_b>1.40607</k_b>
                <k_uds_err>0.014501</k_uds_err>
                <k_c_err>0.0610211</k_c_err>
                <k_b_err>0.119574</k_b_err>
                <sigma_uds_true>0</sigma_uds_true>
                <sigma_c_true>889.849</sigma_c_true>
                <sigma_b_true>62.7154</sigma_b_true>
                <sigma_uds>0</sigma_uds>
                <sigma_c>4182.38</sigma_c>
                <sigma_b>293.942</sigma_b>
                <sigma_uds_err>0</sigma_uds_err>
                <sigma_c_err>180.999</sigma_c_err>
                <sigma_b_err>24.9971</sigma_b_err>
        </bin>
        <bin id="9">
                <subbin>
                        <variable>etajet</variable>
                        <low_edge>1.0</low_edge>
                        <up_edge>1.3</up_edge>
                </subbin>
                <k_uds>0.916627</k_uds>
                <k_c>1.35946</k_c>
                <k_b>1.61623</k_b>
                <k_uds_err>0.0168612</k_uds_err>
                <k_c_err>0.0769236</k_c_err>
                <k_b_err>0.156181</k_b_err>
                <sigma_uds_true>0</sigma_uds_true>
                <sigma_c_true>769.757</sigma_c_true>
                <sigma_b_true>55.9611</sigma_b_true>
                <sigma_uds>0</sigma_uds>
                <sigma_c>3488.17</sigma_c>
                <sigma_b>301.486</sigma_b>
                <sigma_uds_err>0</sigma_uds_err>
                <sigma_c_err>197.375</sigma_c_err>
                <sigma_b_err>29.1336</sigma_b_err>
        </bin>
        <bin id="10">
                <subbin>
                        <variable>etajet</variable>
                        <low_edge>1.3</low_edge>
                        <up_edge>1.6</up_edge>
                </subbin>
                <k_uds>0.810424</k_uds>
                <k_c>1.40527</k_c>
                <k_b>1.4124</k_b>
                <k_uds_err>0.0234813</k_uds_err>
                <k_c_err>0.119507</k_c_err>
                <k_b_err>0.240855</k_b_err>
                <sigma_uds_true>0</sigma_uds_true>
                <sigma_c_true>660.966</sigma_c_true>
                <sigma_b_true>48.198</sigma_b_true>
                <sigma_uds>0</sigma_uds>
                <sigma_c>3096.11</sigma_c>
                <sigma_b>226.916</sigma_b>
                <sigma_uds_err>0</sigma_uds_err>
                <sigma_c_err>263.3</sigma_c_err>
                <sigma_b_err>38.6958</sigma_b_err>
        </bin>
        <bin id="11">
                <subbin>
                        <variable>etajet</variable>
                        <low_edge>1.6</low_edge>
                        <up_edge>2.2</up_edge>
                </subbin>
                <k_uds>0.654741</k_uds>
                <k_c>1.72016</k_c>
                <k_b>1.40698</k_b>
                <k_uds_err>0.0368057</k_uds_err>
                <k_c_err>0.2274</k_c_err>
                <k_b_err>0.448127</k_b_err>
                <sigma_uds_true>0</sigma_uds_true>
                <sigma_c_true>1034.12</sigma_c_true>
                <sigma_b_true>74.4454</sigma_b_true>
                <sigma_uds>0</sigma_uds>
                <sigma_c>2964.76</sigma_c>
                <sigma_b>174.572</sigma_b>
                <sigma_uds_err>0</sigma_uds_err>
                <sigma_c_err>391.934</sigma_c_err>
                <sigma_b_err>55.6016</sigma_b_err>
        </bin>
        </bin_group>
        <!-- et jet -->
        <bin id="12" type="inlcusive">
                <subbin>
                        <variable>etjet</variable>
                        <low_edge>5</low_edge>
                        <up_edge>10000.0</up_edge>
                </subbin>
                <k_uds>0.907631</k_uds>
                <k_c>1.27032</k_c>
                <k_b>1.4668</k_b>
                <k_uds_err>0.00477645</k_uds_err>
                <k_c_err>0.0199508</k_c_err>
                <k_b_err>0.0502009</k_b_err>
                <sigma_uds_true>0</sigma_uds_true>
                <sigma_c_true>9441.9</sigma_c_true>
                <sigma_b_true>599.598</sigma_b_true>
                <sigma_uds>0</sigma_uds>
                <sigma_c>1.20002</sigma_c>
                <sigma_b>0.0879932</sigma_b>
                <sigma_uds_err>0</sigma_uds_err>
                <sigma_c_err>0.0188467</sigma_c_err>
                <sigma_b_err>0.00301154</sigma_b_err>
        </bin>
        <bin_group id="etjet">
        <bin id="13">
                <subbin>
                        <variable>etjet</variable>
                        <low_edge>5</low_edge>
                        <up_edge>8.0</up_edge>
                </subbin>
                <k_uds>0.926053</k_uds>
                <k_c>1.19609</k_c>
                <k_b>1.56044</k_b>
                <k_uds_err>0.00892885</k_uds_err>
                <k_c_err>0.0393435</k_c_err>
                <k_b_err>0.211285</k_b_err>
                <sigma_uds_true>0</sigma_uds_true>
                <sigma_c_true>7111.33</sigma_c_true>
                <sigma_b_true>335.949</sigma_b_true>
                <sigma_uds>0</sigma_uds>
                <sigma_c>2835.26</sigma_c>
                <sigma_b>174.742</sigma_b>
                <sigma_uds_err>0</sigma_uds_err>
                <sigma_c_err>93.2616</sigma_c_err>
                <sigma_b_err>23.6603</sigma_b_err>
        </bin>
        <bin id="14">
                <subbin>
                        <variable>etjet</variable>
                        <low_edge>8.0</low_edge>
                        <up_edge>11.0</up_edge>
                </subbin>
                <k_uds>0.892439</k_uds>
                <k_c>1.33452</k_c>
                <k_b>1.38078</k_b>
                <k_uds_err>0.00922206</k_uds_err>
                <k_c_err>0.0394124</k_c_err>
                <k_b_err>0.0968103</k_b_err>
                <sigma_uds_true>0</sigma_uds_true>
                <sigma_c_true>1597.18</sigma_c_true>
                <sigma_b_true>162.812</sigma_b_true>
                <sigma_uds>0</sigma_uds>
                <sigma_c>710.494</sigma_c>
                <sigma_b>74.9359</sigma_b>
                <sigma_uds_err>0</sigma_uds_err>
                <sigma_c_err>20.983</sigma_c_err>
                <sigma_b_err>5.25396</sigma_b_err>
        </bin>
        <bin id="15">
                <subbin>
                        <variable>etjet</variable>
                        <low_edge>11.0</low_edge>
                        <up_edge>14.0</up_edge>
                </subbin>
                <k_uds>0.882904</k_uds>
                <k_c>1.38523</k_c>
                <k_b>1.41136</k_b>
                <k_uds_err>0.0135771</k_uds_err>
                <k_c_err>0.0624825</k_c_err>
                <k_b_err>0.0857174</k_b_err>
                <sigma_uds_true>0</sigma_uds_true>
                <sigma_c_true>455.794</sigma_c_true>
                <sigma_b_true>60.5849</sigma_b_true>
                <sigma_uds>0</sigma_uds>
                <sigma_c>210.46</sigma_c>
                <sigma_b>28.5024</sigma_b>
                <sigma_uds_err>0</sigma_uds_err>
                <sigma_c_err>9.49305</sigma_c_err>
                <sigma_b_err>1.73106</sigma_b_err>
        </bin>
        <bin id="16">
                <subbin>
                        <variable>etjet</variable>
                        <low_edge>14.0</low_edge>
                        <up_edge>17.0</up_edge>
                </subbin>
                <k_uds>0.865869</k_uds>
                <k_c>1.48411</k_c>
                <k_b>1.41878</k_b>
                <k_uds_err>0.0205267</k_uds_err>
                <k_c_err>0.103248</k_c_err>
                <k_b_err>0.098979</k_b_err>
                <sigma_uds_true>0</sigma_uds_true>
                <sigma_c_true>162.664</sigma_c_true>
                <sigma_b_true>23.7725</sigma_b_true>
                <sigma_uds>0</sigma_uds>
                <sigma_c>80.4707</sigma_c>
                <sigma_b>11.2426</sigma_b>
                <sigma_uds_err>0</sigma_uds_err>
                <sigma_c_err>5.59822</sigma_c_err>
                <sigma_b_err>0.784326</sigma_b_err>
        </bin>
        <bin id="17">
                <subbin>
                        <variable>etjet</variable>
                        <low_edge>17.0</low_edge>
                        <up_edge>20.0</up_edge>
                </subbin>
                <k_uds>0.857959</k_uds>
                <k_c>1.58405</k_c>
                <k_b>1.27253</k_b>
                <k_uds_err>0.0300596</k_uds_err>
                <k_c_err>0.171508</k_c_err>
                <k_b_err>0.145497</k_b_err>
                <sigma_uds_true>0</sigma_uds_true>
                <sigma_c_true>66.4527</sigma_c_true>
                <sigma_b_true>9.78113</sigma_b_true>
                <sigma_uds>0</sigma_uds>
                <sigma_c>35.0882</sigma_c>
                <sigma_b>4.14892</sigma_b>
                <sigma_uds_err>0</sigma_uds_err>
                <sigma_c_err>3.79905</sigma_c_err>
                <sigma_b_err>0.474374</sigma_b_err>
        </bin>
        <bin id="18">
                <subbin>
                        <variable>etjet</variable>
                        <low_edge>20.0</low_edge>
                        <up_edge>25.0</up_edge>
                </subbin>
                <k_uds>0.872946</k_uds>
                <k_c>1.50386</k_c>
                <k_b>1.56149</k_b>
                <k_uds_err>0.0406757</k_uds_err>
                <k_c_err>0.271835</k_c_err>
                <k_b_err>0.204894</k_b_err>
                <sigma_uds_true>0</sigma_uds_true>
                <sigma_c_true>39.5603</sigma_c_true>
                <sigma_b_true>5.70475</sigma_b_true>
                <sigma_uds>0</sigma_uds>
                <sigma_c>11.8986</sigma_c>
                <sigma_b>1.78158</sigma_b>
                <sigma_uds_err>0</sigma_uds_err>
                <sigma_c_err>2.15077</sigma_c_err>
                <sigma_b_err>0.233774</sigma_b_err>
        </bin>
        <bin id="19">
                <subbin>
                        <variable>etjet</variable>
                        <low_edge>25.0</low_edge>
                        <up_edge>35.0</up_edge>
                </subbin>
                <k_uds>0.925959</k_uds>
                <k_c>1.12022</k_c>
                <k_b>1.73465</k_b>
                <k_uds_err>0.0996702</k_uds_err>
                <k_c_err>0.813309</k_c_err>
                <k_b_err>0.452694</k_b_err>
                <sigma_uds_true>0</sigma_uds_true>
                <sigma_c_true>12.6605</sigma_c_true>
                <sigma_b_true>2.03266</sigma_b_true>
                <sigma_uds>0</sigma_uds>
                <sigma_c>1.41826</sigma_c>
                <sigma_b>0.352597</sigma_b>
                <sigma_uds_err>0</sigma_uds_err>
                <sigma_c_err>1.02969</sigma_c_err>
                <sigma_b_err>0.0920175</sigma_b_err>
        </bin>
        </bin_group>
        <!-- phi jet -->
        <bin id="20" type="inlcusive">
                <subbin>
                        <variable>phijet</variable>
                        <low_edge>0</low_edge>
                        <up_edge>6.283</up_edge>
                </subbin>
                <k_uds>0.907625</k_uds>
                <k_c>1.27034</k_c>
                <k_b>1.4667</k_b>
                <k_uds_err>0.00477643</k_uds_err>
                <k_c_err>0.0199507</k_c_err>
                <k_b_err>0.0502016</k_b_err>
                <sigma_uds_true>0</sigma_uds_true>
                <sigma_c_true>9441.63</sigma_c_true>
                <sigma_b_true>599.582</sigma_b_true>
                <sigma_uds>0</sigma_uds>
                <sigma_c>1908.98</sigma_c>
                <sigma_b>139.967</sigma_b>
                <sigma_uds_err>0</sigma_uds_err>
                <sigma_c_err>29.9804</sigma_c_err>
                <sigma_b_err>4.79071</sigma_b_err>
        </bin>
        <bin_group id="phijet">
        <bin id="21">
                <subbin>
                        <variable>phijet</variable>
                        <low_edge>0</low_edge>
                        <up_edge>0.785398</up_edge>
                </subbin>
                <k_uds>0.849711</k_uds>
                <k_c>1.33818</k_c>
                <k_b>1.2454</k_b>
                <k_uds_err>0.0138605</k_uds_err>
                <k_c_err>0.0595064</k_c_err>
                <k_b_err>0.149138</k_b_err>
                <sigma_uds_true>0</sigma_uds_true>
                <sigma_c_true>1182.48</sigma_c_true>
                <sigma_b_true>74.9768</sigma_b_true>
                <sigma_uds>0</sigma_uds>
                <sigma_c>2014.73</sigma_c>
                <sigma_b>118.891</sigma_b>
                <sigma_uds_err>0</sigma_uds_err>
                <sigma_c_err>89.5916</sigma_c_err>
                <sigma_b_err>14.2373</sigma_b_err>
        </bin>
        <bin id="22">
                <subbin>
                        <variable>phijet</variable>
                        <low_edge>0.785398</low_edge>
                        <up_edge>1.5708</up_edge>
                </subbin>
                <k_uds>0.93156</k_uds>
                <k_c>1.24526</k_c>
                <k_b>1.37232</k_b>
                <k_uds_err>0.0116643</k_uds_err>
                <k_c_err>0.0500711</k_c_err>
                <k_b_err>0.149102</k_b_err>
                <sigma_uds_true>0</sigma_uds_true>
                <sigma_c_true>1181.14</sigma_c_true>
                <sigma_b_true>75.2</sigma_b_true>
                <sigma_uds>0</sigma_uds>
                <sigma_c>1872.71</sigma_c>
                <sigma_b>131.396</sigma_b>
                <sigma_uds_err>0</sigma_uds_err>
                <sigma_c_err>75.3002</sigma_c_err>
                <sigma_b_err>14.2761</sigma_b_err>
        </bin>
        <bin id="23">
                <subbin>
                        <variable>phijet</variable>
                        <low_edge>1.5708</low_edge>
                        <up_edge>2.35619</up_edge>
                </subbin>
                <k_uds>0.897969</k_uds>
                <k_c>1.32979</k_c>
                <k_b>1.32719</k_b>
                <k_uds_err>0.0107695</k_uds_err>
                <k_c_err>0.045204</k_c_err>
                <k_b_err>0.124468</k_b_err>
                <sigma_uds_true>0</sigma_uds_true>
                <sigma_c_true>1182.27</sigma_c_true>
                <sigma_b_true>74.9873</sigma_b_true>
                <sigma_uds>0</sigma_uds>
                <sigma_c>2001.78</sigma_c>
                <sigma_b>126.717</sigma_b>
                <sigma_uds_err>0</sigma_uds_err>
                <sigma_c_err>68.0471</sigma_c_err>
                <sigma_b_err>11.8839</sigma_b_err>
        </bin>
        <bin id="24">
                <subbin>
                        <variable>phijet</variable>
                        <low_edge>2.35619</low_edge>
                        <up_edge>3.14159</up_edge>
                </subbin>
                <k_uds>0.927556</k_uds>
                <k_c>1.29337</k_c>
                <k_b>1.47172</k_b>
                <k_uds_err>0.0208378</k_uds_err>
                <k_c_err>0.0827759</k_c_err>
                <k_b_err>0.16702</k_b_err>
                <sigma_uds_true>0</sigma_uds_true>
                <sigma_c_true>1186</sigma_c_true>
                <sigma_b_true>75.3094</sigma_b_true>
                <sigma_uds>0</sigma_uds>
                <sigma_c>1953.05</sigma_c>
                <sigma_b>141.118</sigma_b>
                <sigma_uds_err>0</sigma_uds_err>
                <sigma_c_err>124.996</sigma_c_err>
                <sigma_b_err>16.015</sigma_b_err>
        </bin>
        <bin id="25">
                <subbin>
                        <variable>phijet</variable>
                        <low_edge>3.14159</low_edge>
                        <up_edge>3.92699</up_edge>
                </subbin>
                <k_uds>0.922557</k_uds>
                <k_c>1.13415</k_c>
                <k_b>1.70829</k_b>
                <k_uds_err>0.0309476</k_uds_err>
                <k_c_err>0.123335</k_c_err>
                <k_b_err>0.203812</k_b_err>
                <sigma_uds_true>0</sigma_uds_true>
                <sigma_c_true>1183.96</sigma_c_true>
                <sigma_b_true>75.0247</sigma_b_true>
                <sigma_uds>0</sigma_uds>
                <sigma_c>1709.68</sigma_c>
                <sigma_b>163.183</sigma_b>
                <sigma_uds_err>0</sigma_uds_err>
                <sigma_c_err>185.923</sigma_c_err>
                <sigma_b_err>19.469</sigma_b_err>
        </bin>
        <bin id="26">
                <subbin>
                        <variable>phijet</variable>
                        <low_edge>3.92699</low_edge>
                        <up_edge>4.71239</up_edge>
                </subbin>
                <k_uds>0.930921</k_uds>
                <k_c>1.20299</k_c>
                <k_b>1.49666</k_b>
                <k_uds_err>0.0132691</k_uds_err>
                <k_c_err>0.0547557</k_c_err>
                <k_b_err>0.13116</k_b_err>
                <sigma_uds_true>0</sigma_uds_true>
                <sigma_c_true>1185.17</sigma_c_true>
                <sigma_b_true>75.2135</sigma_b_true>
                <sigma_uds>0</sigma_uds>
                <sigma_c>1815.31</sigma_c>
                <sigma_b>143.327</sigma_b>
                <sigma_uds_err>0</sigma_uds_err>
                <sigma_c_err>82.6265</sigma_c_err>
                <sigma_b_err>12.5605</sigma_b_err>
        </bin>
        <bin id="27">
                <subbin>
                        <variable>phijet</variable>
                        <low_edge>4.71239</low_edge>
                        <up_edge>5.49779</up_edge>
                </subbin>
                <k_uds>0.921112</k_uds>
                <k_c>1.27686</k_c>
                <k_b>1.62192</k_b>
                <k_uds_err>0.00982093</k_uds_err>
                <k_c_err>0.0415508</k_c_err>
                <k_b_err>0.115523</k_b_err>
                <sigma_uds_true>0</sigma_uds_true>
                <sigma_c_true>1182.38</sigma_c_true>
                <sigma_b_true>75.0458</sigma_b_true>
                <sigma_uds>0</sigma_uds>
                <sigma_c>1922.25</sigma_c>
                <sigma_b>154.976</sigma_b>
                <sigma_uds_err>0</sigma_uds_err>
                <sigma_c_err>62.5525</sigma_c_err>
                <sigma_b_err>11.0383</sigma_b_err>
        </bin>
        <bin id="28">
                <subbin>
                        <variable>phijet</variable>
                        <low_edge>5.49779</low_edge>
                        <up_edge>6.28319</up_edge>
                </subbin>
                <k_uds>0.89376</k_uds>
                <k_c>1.26169</k_c>
                <k_b>1.48435</k_b>
                <k_uds_err>0.0133538</k_uds_err>
                <k_c_err>0.0559014</k_c_err>
                <k_b_err>0.132412</k_b_err>
                <sigma_uds_true>0</sigma_uds_true>
                <sigma_c_true>1181.18</sigma_c_true>
                <sigma_b_true>75.0679</sigma_b_true>
                <sigma_uds>0</sigma_uds>
                <sigma_c>1897.48</sigma_c>
                <sigma_b>141.873</sigma_b>
                <sigma_uds_err>0</sigma_uds_err>
                <sigma_c_err>84.0711</sigma_c_err>
                <sigma_b_err>12.6559</sigma_b_err>
        </bin>
        </bin_group>
        <!-- xda -->
        <bin id="29" type="inlcusive">
                <subbin>
                        <variable>xda</variable>
                        <low_edge>0</low_edge>
                        <up_edge>1</up_edge>
                </subbin>
                <k_uds>0.907631</k_uds>
                <k_c>1.27032</k_c>
                <k_b>1.4668</k_b>
                <k_uds_err>0.00477645</k_uds_err>
                <k_c_err>0.0199508</k_c_err>
                <k_b_err>0.0502009</k_b_err>
                <sigma_uds_true>0</sigma_uds_true>
                <sigma_c_true>9441.9</sigma_c_true>
                <sigma_b_true>599.598</sigma_b_true>
                <sigma_uds>0</sigma_uds>
                <sigma_c>11994.2</sigma_c>
                <sigma_b>879.492</sigma_b>
                <sigma_uds_err>0</sigma_uds_err>
                <sigma_c_err>188.373</sigma_c_err>
                <sigma_b_err>30.1004</sigma_b_err>
        </bin>
        <bin_group id="xda">
        <bin id="30">
                <subbin>
                        <variable>xda</variable>
                        <low_edge>0.00008</low_edge>
                        <up_edge>0.0002</up_edge>
                </subbin>
                <k_uds>0.888788</k_uds>
                <k_c>1.29311</k_c>
                <k_b>1.31442</k_b>
                <k_uds_err>0.0315408</k_uds_err>
                <k_c_err>0.1009</k_c_err>
                <k_b_err>0.205238</k_b_err>
                <sigma_uds_true>0</sigma_uds_true>
                <sigma_c_true>725.255</sigma_c_true>
                <sigma_b_true>67.4039</sigma_b_true>
                <sigma_uds>0</sigma_uds>
                <sigma_c>7.81531e+06</sigma_c>
                <sigma_b>738308</sigma_b>
                <sigma_uds_err>0</sigma_uds_err>
                <sigma_c_err>609819</sigma_c_err>
                <sigma_b_err>115282</sigma_b_err>
        </bin>
        <bin id="31">
                <subbin>
                        <variable>xda</variable>
                        <low_edge>0.0002</low_edge>
                        <up_edge>0.0006</up_edge>
                </subbin>
                <k_uds>0.842574</k_uds>
                <k_c>1.21003</k_c>
                <k_b>1.48039</k_b>
                <k_uds_err>0.0133067</k_uds_err>
                <k_c_err>0.0447824</k_c_err>
                <k_b_err>0.0988221</k_b_err>
                <sigma_uds_true>0</sigma_uds_true>
                <sigma_c_true>2354.12</sigma_c_true>
                <sigma_b_true>180.838</sigma_b_true>
                <sigma_uds>0</sigma_uds>
                <sigma_c>7.12136e+06</sigma_c>
                <sigma_b>669275</sigma_b>
                <sigma_uds_err>0</sigma_uds_err>
                <sigma_c_err>263557</sigma_c_err>
                <sigma_b_err>44677</sigma_b_err>
        </bin>
        <bin id="32">
                <subbin>
                        <variable>xda</variable>
                        <low_edge>0.0006</low_edge>
                        <up_edge>0.0016</up_edge>
                </subbin>
                <k_uds>0.854657</k_uds>
                <k_c>1.2833</k_c>
                <k_b>1.42588</k_b>
                <k_uds_err>0.0100591</k_uds_err>
                <k_c_err>0.0350501</k_c_err>
                <k_b_err>0.0843057</k_b_err>
                <sigma_uds_true>0</sigma_uds_true>
                <sigma_c_true>2647.27</sigma_c_true>
                <sigma_b_true>163.201</sigma_b_true>
                <sigma_uds>0</sigma_uds>
                <sigma_c>3.39724e+06</sigma_c>
                <sigma_b>232704</sigma_b>
                <sigma_uds_err>0</sigma_uds_err>
                <sigma_c_err>92787.2</sigma_c_err>
                <sigma_b_err>13758.8</sigma_b_err>
        </bin>
        <bin id="33">
                <subbin>
                        <variable>xda</variable>
                        <low_edge>0.0016</low_edge>
                        <up_edge>0.005</up_edge>
                </subbin>
                <k_uds>0.939074</k_uds>
                <k_c>1.28352</k_c>
                <k_b>1.41383</k_b>
                <k_uds_err>0.00807734</k_uds_err>
                <k_c_err>0.0336798</k_c_err>
                <k_b_err>0.0902915</k_b_err>
                <sigma_uds_true>0</sigma_uds_true>
                <sigma_c_true>2331.75</sigma_c_true>
                <sigma_b_true>125.557</sigma_b_true>
                <sigma_uds>0</sigma_uds>
                <sigma_c>880254</sigma_c>
                <sigma_b>52210.6</sigma_b>
                <sigma_uds_err>0</sigma_uds_err>
                <sigma_c_err>23097.9</sigma_c_err>
                <sigma_b_err>3334.33</sigma_b_err>
        </bin>
        <bin id="34">
                <subbin>
                        <variable>xda</variable>
                        <low_edge>0.005</low_edge>
                        <up_edge>0.01</up_edge>
                </subbin>
                <k_uds>0.968908</k_uds>
                <k_c>1.25425</k_c>
                <k_b>1.64078</k_b>
                <k_uds_err>0.0114207</k_uds_err>
                <k_c_err>0.0602427</k_c_err>
                <k_b_err>0.160673</k_b_err>
                <sigma_uds_true>0</sigma_uds_true>
                <sigma_c_true>810.675</sigma_c_true>
                <sigma_b_true>38.8056</sigma_b_true>
                <sigma_uds>0</sigma_uds>
                <sigma_c>203358</sigma_c>
                <sigma_b>12734.3</sigma_b>
                <sigma_uds_err>0</sigma_uds_err>
                <sigma_c_err>9767.45</sigma_c_err>
                <sigma_b_err>1247</sigma_b_err>
        </bin>
        <bin id="35">
                <subbin>
                        <variable>xda</variable>
                        <low_edge>0.01</low_edge>
                        <up_edge>0.1</up_edge>
                </subbin>
                <k_uds>0.935228</k_uds>
                <k_c>1.37567</k_c>
                <k_b>1.38052</k_b>
                <k_uds_err>0.0134445</k_uds_err>
                <k_c_err>0.104664</k_c_err>
                <k_b_err>0.264305</k_b_err>
                <sigma_uds_true>0</sigma_uds_true>
                <sigma_c_true>584.111</sigma_c_true>
                <sigma_b_true>23.9374</sigma_b_true>
                <sigma_uds>0</sigma_uds>
                <sigma_c>8928.25</sigma_c>
                <sigma_b>367.178</sigma_b>
                <sigma_uds_err>0</sigma_uds_err>
                <sigma_c_err>679.284</sigma_c_err>
                <sigma_b_err>70.2974</sigma_b_err>
        </bin>
        </bin_group>
        <bin id="36">
                <subbin>
                        <variable>q2da</variable>
                        <low_edge>5.0</low_edge>
                        <up_edge>1000.0</up_edge>
                </subbin>
                <k_uds>0.907631</k_uds>
                <k_c>1.27032</k_c>
                <k_b>1.4668</k_b>
                <k_uds_err>0.00477645</k_uds_err>
                <k_c_err>0.0199508</k_c_err>
                <k_b_err>0.0502009</k_b_err>
                <sigma_uds_true>0</sigma_uds_true>
                <sigma_c_true>9441.9</sigma_c_true>
                <sigma_b_true>599.598</sigma_b_true>
                <sigma_uds>0</sigma_uds>
                <sigma_c>12.0545</sigma_c>
                <sigma_b>0.883912</sigma_b>
                <sigma_uds_err>0</sigma_uds_err>
                <sigma_c_err>0.18932</sigma_c_err>
                <sigma_b_err>0.0302516</sigma_b_err>
        </bin>
        <bin_group id="q2da">
        <bin id="37">
                <subbin>
                        <variable>q2da</variable>
                        <low_edge>5.0</low_edge>
                        <up_edge>10.0</up_edge>
                </subbin>
                <k_uds>0.869882</k_uds>
                <k_c>1.21714</k_c>
                <k_b>1.61036</k_b>
                <k_uds_err>0.0137795</k_uds_err>
                <k_c_err>0.0520676</k_c_err>
                <k_b_err>0.13932</k_b_err>
                <sigma_uds_true>0</sigma_uds_true>
                <sigma_c_true>2124.83</sigma_c_true>
                <sigma_b_true>146.935</sigma_b_true>
                <sigma_uds>0</sigma_uds>
                <sigma_c>517.242</sigma_c>
                <sigma_b>47.3237</sigma_b>
                <sigma_uds_err>0</sigma_uds_err>
                <sigma_c_err>22.127</sigma_c_err>
                <sigma_b_err>4.09419</sigma_b_err>
        </bin>
        <bin id="38">
                <subbin>
                        <variable>q2da</variable>
                        <low_edge>10.0</low_edge>
                        <up_edge>20.0</up_edge>
                </subbin>
                <k_uds>0.86765</k_uds>
                <k_c>1.29255</k_c>
                <k_b>1.41022</k_b>
                <k_uds_err>0.0109713</k_uds_err>
                <k_c_err>0.0423366</k_c_err>
                <k_b_err>0.117393</k_b_err>
                <sigma_uds_true>0</sigma_uds_true>
                <sigma_c_true>2297.81</sigma_c_true>
                <sigma_b_true>139.026</sigma_b_true>
                <sigma_uds>0</sigma_uds>
                <sigma_c>297.004</sigma_c>
                <sigma_b>19.6058</sigma_b>
                <sigma_uds_err>0</sigma_uds_err>
                <sigma_c_err>9.72814</sigma_c_err>
                <sigma_b_err>1.63208</sigma_b_err>
        </bin>
        <bin id="39">
                <subbin>
                        <variable>q2da</variable>
                        <low_edge>20.0</low_edge>
                        <up_edge>40.0</up_edge>
                </subbin>
                <k_uds>0.896585</k_uds>
                <k_c>1.33228</k_c>
                <k_b>1.35781</k_b>
                <k_uds_err>0.00979632</k_uds_err>
                <k_c_err>0.0406891</k_c_err>
                <k_b_err>0.1179</k_b_err>
                <sigma_uds_true>0</sigma_uds_true>
                <sigma_c_true>2219.15</sigma_c_true>
                <sigma_b_true>122.111</sigma_b_true>
                <sigma_uds>0</sigma_uds>
                <sigma_c>147.827</sigma_c>
                <sigma_b>8.2902</sigma_b>
                <sigma_uds_err>0</sigma_uds_err>
                <sigma_c_err>4.51477</sigma_c_err>
                <sigma_b_err>0.719846</sigma_b_err>
        </bin>
        <bin id="40">
                <subbin>
                        <variable>q2da</variable>
                        <low_edge>40.0</low_edge>
                        <up_edge>70.0</up_edge>
                </subbin>
                <k_uds>0.922275</k_uds>
                <k_c>1.20367</k_c>
                <k_b>1.50564</k_b>
                <k_uds_err>0.0112882</k_uds_err>
                <k_c_err>0.0502883</k_c_err>
                <k_b_err>0.138147</k_b_err>
                <sigma_uds_true>0</sigma_uds_true>
                <sigma_c_true>1338.02</sigma_c_true>
                <sigma_b_true>78.5205</sigma_b_true>
                <sigma_uds>0</sigma_uds>
                <sigma_c>53.6845</sigma_c>
                <sigma_b>3.94079</sigma_b>
                <sigma_uds_err>0</sigma_uds_err>
                <sigma_c_err>2.24289</sigma_c_err>
                <sigma_b_err>0.36158</sigma_b_err>
        </bin>
        <bin id="41">
                <subbin>
                        <variable>q2da</variable>
                        <low_edge>70.0</low_edge>
                        <up_edge>120.0</up_edge>
                </subbin>
                <k_uds>0.91985</k_uds>
                <k_c>1.28631</k_c>
                <k_b>1.25747</k_b>
                <k_uds_err>0.0129186</k_uds_err>
                <k_c_err>0.0587162</k_c_err>
                <k_b_err>0.133831</k_b_err>
                <sigma_uds_true>0</sigma_uds_true>
                <sigma_c_true>768.776</sigma_c_true>
                <sigma_b_true>53.799</sigma_b_true>
                <sigma_uds>0</sigma_uds>
                <sigma_c>19.7777</sigma_c>
                <sigma_b>1.35301</sigma_b>
                <sigma_uds_err>0</sigma_uds_err>
                <sigma_c_err>0.902793</sigma_c_err>
                <sigma_b_err>0.143999</sigma_b_err>
        </bin>
        <bin id="42">
                <subbin>
                        <variable>q2da</variable>
                        <low_edge>120.0</low_edge>
                        <up_edge>200.0</up_edge>
                </subbin>
                <k_uds>0.954303</k_uds>
                <k_c>1.26358</k_c>
                <k_b>1.69193</k_b>
                <k_uds_err>0.0181297</k_uds_err>
                <k_c_err>0.0847798</k_c_err>
                <k_b_err>0.164593</k_b_err>
                <sigma_uds_true>0</sigma_uds_true>
                <sigma_c_true>385.71</sigma_c_true>
                <sigma_b_true>31.8645</sigma_b_true>
                <sigma_uds>0</sigma_uds>
                <sigma_c>6.0922</sigma_c>
                <sigma_b>0.673904</sigma_b>
                <sigma_uds_err>0</sigma_uds_err>
                <sigma_c_err>0.408756</sigma_c_err>
                <sigma_b_err>0.0655585</sigma_b_err>
        </bin>
        <bin id="43">
                <subbin>
                        <variable>q2da</variable>
                        <low_edge>200.0</low_edge>
                        <up_edge>400.0</up_edge>
                </subbin>
                <k_uds>0.992468</k_uds>
                <k_c>1.36378</k_c>
                <k_b>1.47657</k_b>
                <k_uds_err>0.0213115</k_uds_err>
                <k_c_err>0.100394</k_c_err>
                <k_b_err>0.162148</k_b_err>
                <sigma_uds_true>0</sigma_uds_true>
                <sigma_c_true>234.105</sigma_c_true>
                <sigma_b_true>20.645</sigma_b_true>
                <sigma_uds>0</sigma_uds>
                <sigma_c>1.59633</sigma_c>
                <sigma_b>0.152419</sigma_b>
                <sigma_uds_err>0</sigma_uds_err>
                <sigma_c_err>0.117514</sigma_c_err>
                <sigma_b_err>0.0167377</sigma_b_err>
        </bin>
        <bin id="44">
                <subbin>
                        <variable>q2da</variable>
                        <low_edge>400.0</low_edge>
                        <up_edge>1000.0</up_edge>
                </subbin>
                <k_uds>1.13306</k_uds>
                <k_c>1.10549</k_c>
                <k_b>1.45512</k_b>
                <k_uds_err>0.0366963</k_uds_err>
                <k_c_err>0.176681</k_c_err>
                <k_b_err>0.25414</k_b_err>
                <sigma_uds_true>0</sigma_uds_true>
                <sigma_c_true>93.2332</sigma_c_true>
                <sigma_b_true>7.79</sigma_b_true>
                <sigma_uds>0</sigma_uds>
                <sigma_c>0.171781</sigma_c>
                <sigma_b>0.0188923</sigma_b>
                <sigma_uds_err>0</sigma_uds_err>
                <sigma_c_err>0.0274542</sigma_c_err>
                <sigma_b_err>0.00329959</sigma_b_err>
        </bin>
        </bin_group>
        <bin_group id="q2da_xda_bin1">
        <bin id="45">
                <subbin>
                        <variable>q2da</variable>
                        <low_edge>5.0</low_edge>
                        <up_edge>20.0</up_edge>
                </subbin>
                <subbin>
                        <variable>xda</variable>
                        <low_edge>0.00008</low_edge>
                        <up_edge>0.0002</up_edge>
                </subbin>
                <k_uds>0.888788</k_uds>
                <k_c>1.29311</k_c>
                <k_b>1.31442</k_b>
                <k_uds_err>0.0315408</k_uds_err>
                <k_c_err>0.1009</k_c_err>
                <k_b_err>0.205238</k_b_err>
                <sigma_uds_true>0</sigma_uds_true>
                <sigma_c_true>725.255</sigma_c_true>
                <sigma_b_true>67.4039</sigma_b_true>
                <sigma_uds>0</sigma_uds>
                <sigma_c>7.81531e+06</sigma_c>
                <sigma_b>738308</sigma_b>
                <sigma_uds_err>0</sigma_uds_err>
                <sigma_c_err>609819</sigma_c_err>
                <sigma_b_err>115282</sigma_b_err>
        </bin>
        <bin id="46">
                <subbin>
                        <variable>q2da</variable>
                        <low_edge>5.0</low_edge>
                        <up_edge>20.0</up_edge>
                </subbin>
                <subbin>
                        <variable>xda</variable>
                        <low_edge>0.0002</low_edge>
                        <up_edge>0.0003</up_edge>
                </subbin>
                <k_uds>0.864939</k_uds>
                <k_c>1.26553</k_c>
                <k_b>1.44639</k_b>
                <k_uds_err>0.026897</k_uds_err>
                <k_c_err>0.0878322</k_c_err>
                <k_b_err>0.187867</k_b_err>
                <sigma_uds_true>0</sigma_uds_true>
                <sigma_c_true>696.99</sigma_c_true>
                <sigma_b_true>59.5431</sigma_b_true>
                <sigma_uds>0</sigma_uds>
                <sigma_c>8.8206e+06</sigma_c>
                <sigma_b>861226</sigma_b>
                <sigma_uds_err>0</sigma_uds_err>
                <sigma_c_err>612182</sigma_c_err>
                <sigma_b_err>111862</sigma_b_err>
        </bin>
        <bin id="47">
                <subbin>
                        <variable>q2da</variable>
                        <low_edge>5.0</low_edge>
                        <up_edge>20.0</up_edge>
                </subbin>
                <subbin>
                        <variable>xda</variable>
                        <low_edge>0.0003</low_edge>
                        <up_edge>0.0005</up_edge>
                </subbin>
                <k_uds>0.850516</k_uds>
                <k_c>1.14162</k_c>
                <k_b>1.55961</k_b>
                <k_uds_err>0.0192088</k_uds_err>
                <k_c_err>0.0670452</k_c_err>
                <k_b_err>0.156847</k_b_err>
                <sigma_uds_true>0</sigma_uds_true>
                <sigma_c_true>999.665</sigma_c_true>
                <sigma_b_true>71.0644</sigma_b_true>
                <sigma_uds>0</sigma_uds>
                <sigma_c>5.70621e+06</sigma_c>
                <sigma_b>554163</sigma_b>
                <sigma_uds_err>0</sigma_uds_err>
                <sigma_c_err>335114</sigma_c_err>
                <sigma_b_err>55731.2</sigma_b_err>
        </bin>
        <bin id="48">
                <subbin>
                        <variable>q2da</variable>
                        <low_edge>5.0</low_edge>
                        <up_edge>20.0</up_edge>
                </subbin>
                <subbin>
                        <variable>xda</variable>
                        <low_edge>0.0005</low_edge>
                        <up_edge>0.003</up_edge>
                </subbin>
                <k_uds>0.861643</k_uds>
                <k_c>1.27722</k_c>
                <k_b>1.50921</k_b>
                <k_uds_err>0.0112946</k_uds_err>
                <k_c_err>0.0458132</k_c_err>
                <k_b_err>0.154012</k_b_err>
                <sigma_uds_true>0</sigma_uds_true>
                <sigma_c_true>1887.73</sigma_c_true>
                <sigma_b_true>85.8301</sigma_b_true>
                <sigma_uds>0</sigma_uds>
                <sigma_c>964421</sigma_c>
                <sigma_b>51814.2</sigma_b>
                <sigma_uds_err>0</sigma_uds_err>
                <sigma_c_err>34593.2</sigma_c_err>
                <sigma_b_err>5287.54</sigma_b_err>
        </bin>
        </bin_group>
        <bin_group id="q2da_xda_bin2">
        <bin id="49">
                <subbin>
                        <variable>q2da</variable>
                        <low_edge>20.0</low_edge>
                        <up_edge>60.0</up_edge>
                </subbin>
                <subbin>
                        <variable>xda</variable>
                        <low_edge>0.0003</low_edge>
                        <up_edge>0.0005</up_edge>
                </subbin>
                <k_uds>0.770879</k_uds>
                <k_c>1.38394</k_c>
                <k_b>1.07912</k_b>
                <k_uds_err>0.0675393</k_uds_err>
                <k_c_err>0.190201</k_c_err>
                <k_b_err>0.286343</k_b_err>
                <sigma_uds_true>0</sigma_uds_true>
                <sigma_c_true>180.469</sigma_c_true>
                <sigma_b_true>17.4859</sigma_b_true>
                <sigma_uds>0</sigma_uds>
                <sigma_c>1.24879e+06</sigma_c>
                <sigma_b>94346.9</sigma_b>
                <sigma_uds_err>0</sigma_uds_err>
                <sigma_c_err>171627</sigma_c_err>
                <sigma_b_err>25034.8</sigma_b_err>
        </bin>
        <bin id="50">
                <subbin>
                        <variable>q2da</variable>
                        <low_edge>20.0</low_edge>
                        <up_edge>60.0</up_edge>
                </subbin>
                <subbin>
                        <variable>xda</variable>
                        <low_edge>0.0005</low_edge>
                        <up_edge>0.0012</up_edge>
                </subbin>
                <k_uds>0.831258</k_uds>
                <k_c>1.3624</k_c>
                <k_b>1.28744</k_b>
                <k_uds_err>0.0193688</k_uds_err>
                <k_c_err>0.0586371</k_c_err>
                <k_b_err>0.111101</k_b_err>
                <sigma_uds_true>0</sigma_uds_true>
                <sigma_c_true>991.826</sigma_c_true>
                <sigma_b_true>78.9184</sigma_b_true>
                <sigma_uds>0</sigma_uds>
                <sigma_c>1.93037e+06</sigma_c>
                <sigma_b>145147</sigma_b>
                <sigma_uds_err>0</sigma_uds_err>
                <sigma_c_err>83082.5</sigma_c_err>
                <sigma_b_err>12525.5</sigma_b_err>
        </bin>
        <bin id="51">
                <subbin>
                        <variable>q2da</variable>
                        <low_edge>20.0</low_edge>
                        <up_edge>60.0</up_edge>
                </subbin>
                <subbin>
                        <variable>xda</variable>
                        <low_edge>0.0012</low_edge>
                        <up_edge>0.002</up_edge>
                </subbin>
                <k_uds>0.920001</k_uds>
                <k_c>1.23205</k_c>
                <k_b>1.42839</k_b>
                <k_uds_err>0.016827</k_uds_err>
                <k_c_err>0.0602045</k_c_err>
                <k_b_err>0.156715</k_b_err>
                <sigma_uds_true>0</sigma_uds_true>
                <sigma_c_true>698.872</sigma_c_true>
                <sigma_b_true>40.4896</sigma_b_true>
                <sigma_uds>0</sigma_uds>
                <sigma_c>1.07631e+06</sigma_c>
                <sigma_b>72293.8</sigma_b>
                <sigma_uds_err>0</sigma_uds_err>
                <sigma_c_err>52594.1</sigma_c_err>
                <sigma_b_err>7931.67</sigma_b_err>
        </bin>
        <bin id="52">
                <subbin>
                        <variable>q2da</variable>
                        <low_edge>20.0</low_edge>
                        <up_edge>60.0</up_edge>
                </subbin>
                <subbin>
                        <variable>xda</variable>
                        <low_edge>0.002</low_edge>
                        <up_edge>0.0035</up_edge>
                </subbin>
                <k_uds>0.952185</k_uds>
                <k_c>1.17431</k_c>
                <k_b>1.60016</k_b>
                <k_uds_err>0.0148397</k_uds_err>
                <k_c_err>0.0627723</k_c_err>
                <k_b_err>0.230726</k_b_err>
                <sigma_uds_true>0</sigma_uds_true>
                <sigma_c_true>624.301</sigma_c_true>
                <sigma_b_true>27.2747</sigma_b_true>
                <sigma_uds>0</sigma_uds>
                <sigma_c>488749</sigma_c>
                <sigma_b>29095.9</sigma_b>
                <sigma_uds_err>0</sigma_uds_err>
                <sigma_c_err>26125.9</sigma_c_err>
                <sigma_b_err>4195.32</sigma_b_err>
        </bin>
        <bin id="53">
                <subbin>
                        <variable>q2da</variable>
                        <low_edge>20.0</low_edge>
                        <up_edge>60.0</up_edge>
                </subbin>
                <subbin>
                        <variable>xda</variable>
                        <low_edge>0.0035</low_edge>
                        <up_edge>0.01</up_edge>
                </subbin>
                <k_uds>0.946487</k_uds>
                <k_c>1.34951</k_c>
                <k_b>1.61623</k_b>
                <k_uds_err>0.0155031</k_uds_err>
                <k_c_err>0.100528</k_c_err>
                <k_b_err>0.684473</k_b_err>
                <sigma_uds_true>0</sigma_uds_true>
                <sigma_c_true>631.016</sigma_c_true>
                <sigma_b_true>16.1517</sigma_b_true>
                <sigma_uds>0</sigma_uds>
                <sigma_c>131010</sigma_c>
                <sigma_b>4016.12</sigma_b>
                <sigma_uds_err>0</sigma_uds_err>
                <sigma_c_err>9759.23</sigma_c_err>
                <sigma_b_err>1700.83</sigma_b_err>
        </bin>
        </bin_group>
        <bin_group id="q2da_xda_bin3">
        <bin id="54">
                <subbin>
                        <variable>q2da</variable>
                        <low_edge>60.0</low_edge>
                        <up_edge>120.0</up_edge>
                </subbin>
                <subbin>
                        <variable>xda</variable>
                        <low_edge>0.0008</low_edge>
                        <up_edge>0.0018</up_edge>
                </subbin>
                <k_uds>0.89812</k_uds>
                <k_c>1.15923</k_c>
                <k_b>1.60694</k_b>
                <k_uds_err>0.0439074</k_uds_err>
                <k_c_err>0.135786</k_c_err>
                <k_b_err>0.196224</k_b_err>
                <sigma_uds_true>0</sigma_uds_true>
                <sigma_c_true>195.285</sigma_c_true>
                <sigma_b_true>19.8865</sigma_b_true>
                <sigma_uds>0</sigma_uds>
                <sigma_c>226379</sigma_c>
                <sigma_b>31956.5</sigma_b>
                <sigma_uds_err>0</sigma_uds_err>
                <sigma_c_err>26516.9</sigma_c_err>
                <sigma_b_err>3902.21</sigma_b_err>
        </bin>
        <bin id="55">
                <subbin>
                        <variable>q2da</variable>
                        <low_edge>60.0</low_edge>
                        <up_edge>120.0</up_edge>
                </subbin>
                <subbin>
                        <variable>xda</variable>
                        <low_edge>0.0018</low_edge>
                        <up_edge>0.003</up_edge>
                </subbin>
                <k_uds>0.947308</k_uds>
                <k_c>1.16217</k_c>
                <k_b>1.37572</k_b>
                <k_uds_err>0.0264823</k_uds_err>
                <k_c_err>0.0923983</k_c_err>
                <k_b_err>0.164043</k_b_err>
                <sigma_uds_true>0</sigma_uds_true>
                <sigma_c_true>252.699</sigma_c_true>
                <sigma_b_true>21.222</sigma_b_true>
                <sigma_uds>0</sigma_uds>
                <sigma_c>244733</sigma_c>
                <sigma_b>24329.7</sigma_b>
                <sigma_uds_err>0</sigma_uds_err>
                <sigma_c_err>19457.5</sigma_c_err>
                <sigma_b_err>2901.1</sigma_b_err>
        </bin>
        <bin id="56">
                <subbin>
                        <variable>q2da</variable>
                        <low_edge>60.0</low_edge>
                        <up_edge>120.0</up_edge>
                </subbin>
                <subbin>
                        <variable>xda</variable>
                        <low_edge>0.003</low_edge>
                        <up_edge>0.006</up_edge>
                </subbin>
                <k_uds>0.950107</k_uds>
                <k_c>1.25877</k_c>
                <k_b>1.18614</k_b>
                <k_uds_err>0.0188722</k_uds_err>
                <k_c_err>0.0761015</k_c_err>
                <k_b_err>0.191617</k_b_err>
                <sigma_uds_true>0</sigma_uds_true>
                <sigma_c_true>295.636</sigma_c_true>
                <sigma_b_true>19.8254</sigma_b_true>
                <sigma_uds>0</sigma_uds>
                <sigma_c>124046</sigma_c>
                <sigma_b>7838.53</sigma_b>
                <sigma_uds_err>0</sigma_uds_err>
                <sigma_c_err>7499.45</sigma_c_err>
                <sigma_b_err>1266.29</sigma_b_err>
        </bin>
        <bin id="57">
                <subbin>
                        <variable>q2da</variable>
                        <low_edge>60.0</low_edge>
                        <up_edge>120.0</up_edge>
                </subbin>
                <subbin>
                        <variable>xda</variable>
                        <low_edge>0.006</low_edge>
                        <up_edge>0.04</up_edge>
                </subbin>
                <k_uds>0.898507</k_uds>
                <k_c>1.41083</k_c>
                <k_b>0.844381</k_b>
                <k_uds_err>0.0181741</k_uds_err>
                <k_c_err>0.124747</k_c_err>
                <k_b_err>0.549368</k_b_err>
                <sigma_uds_true>0</sigma_uds_true>
                <sigma_c_true>335.88</sigma_c_true>
                <sigma_b_true>12.2477</sigma_b_true>
                <sigma_uds>0</sigma_uds>
                <sigma_c>13937.4</sigma_c>
                <sigma_b>304.168</sigma_b>
                <sigma_uds_err>0</sigma_uds_err>
                <sigma_c_err>1232.36</sigma_c_err>
                <sigma_b_err>197.897</sigma_b_err>
        </bin>
        </bin_group>
        <bin_group id="q2da_xda_bin4">
        <bin id="58">
                <subbin>
                        <variable>q2da</variable>
                        <low_edge>120.0</low_edge>
                        <up_edge>400.0</up_edge>
                </subbin>
                <subbin>
                        <variable>xda</variable>
                        <low_edge>0.0016</low_edge>
                        <up_edge>0.005</up_edge>
                </subbin>
                <k_uds>0.818563</k_uds>
                <k_c>1.59899</k_c>
                <k_b>1.05387</k_b>
                <k_uds_err>0.0311802</k_uds_err>
                <k_c_err>0.108209</k_c_err>
                <k_b_err>0.146675</k_b_err>
                <sigma_uds_true>0</sigma_uds_true>
                <sigma_c_true>205.217</sigma_c_true>
                <sigma_b_true>21.5049</sigma_b_true>
                <sigma_uds>0</sigma_uds>
                <sigma_c>96512</sigma_c>
                <sigma_b>6665.67</sigma_b>
                <sigma_uds_err>0</sigma_uds_err>
                <sigma_c_err>6531.29</sigma_c_err>
                <sigma_b_err>927.715</sigma_b_err>
        </bin>
        <bin id="59">
                <subbin>
                        <variable>q2da</variable>
                        <low_edge>120.0</low_edge>
                        <up_edge>400.0</up_edge>
                </subbin>
                <subbin>
                        <variable>xda</variable>
                        <low_edge>0.005</low_edge>
                        <up_edge>0.016</up_edge>
                </subbin>
                <k_uds>1.0367</k_uds>
                <k_c>1.12514</k_c>
                <k_b>1.89399</k_b>
                <k_uds_err>0.0180925</k_uds_err>
                <k_c_err>0.0760421</k_c_err>
                <k_b_err>0.145042</k_b_err>
                <sigma_uds_true>0</sigma_uds_true>
                <sigma_c_true>301.326</sigma_c_true>
                <sigma_b_true>25.8383</sigma_b_true>
                <sigma_uds>0</sigma_uds>
                <sigma_c>30821.4</sigma_c>
                <sigma_b>4448.86</sigma_b>
                <sigma_uds_err>0</sigma_uds_err>
                <sigma_c_err>2083.04</sigma_c_err>
                <sigma_b_err>340.695</sigma_b_err>
        </bin>
        <bin id="60">
                <subbin>
                        <variable>q2da</variable>
                        <low_edge>120.0</low_edge>
                        <up_edge>400.0</up_edge>
                </subbin>
                <subbin>
                        <variable>xda</variable>
                        <low_edge>0.016</low_edge>
                        <up_edge>0.06</up_edge>
                </subbin>
                <k_uds>0.950861</k_uds>
                <k_c>1.58558</k_c>
                <k_b>1.59213</k_b>
                <k_uds_err>0.0311566</k_uds_err>
                <k_c_err>0.297328</k_c_err>
                <k_b_err>0.800583</k_b_err>
                <sigma_uds_true>0</sigma_uds_true>
                <sigma_c_true>110.455</sigma_c_true>
                <sigma_b_true>5.09636</sigma_b_true>
                <sigma_uds>0</sigma_uds>
                <sigma_c>3980.34</sigma_c>
                <sigma_b>184.41</sigma_b>
                <sigma_uds_err>0</sigma_uds_err>
                <sigma_c_err>746.395</sigma_c_err>
                <sigma_b_err>92.7286</sigma_b_err>
        </bin>
        </bin_group>
        <bin_group id="q2da_xda_bin5">
        <bin id="61">
                <subbin>
                        <variable>q2da</variable>
                        <low_edge>400.0</low_edge>
                        <up_edge>1000.0</up_edge>
                </subbin>
                <subbin>
                        <variable>xda</variable>
                        <low_edge>0.005</low_edge>
                        <up_edge>0.02</up_edge>
                </subbin>
                <k_uds>1.08231</k_uds>
                <k_c>1.11218</k_c>
                <k_b>1.1379</k_b>
                <k_uds_err>0.0503014</k_uds_err>
                <k_c_err>0.177033</k_c_err>
                <k_b_err>0.240613</k_b_err>
                <sigma_uds_true>0</sigma_uds_true>
                <sigma_c_true>57.7822</sigma_c_true>
                <sigma_b_true>5.45056</sigma_b_true>
                <sigma_uds>0</sigma_uds>
                <sigma_c>4284.28</sigma_c>
                <sigma_b>413.478</sigma_b>
                <sigma_uds_err>0</sigma_uds_err>
                <sigma_c_err>681.957</sigma_c_err>
                <sigma_b_err>87.4318</sigma_b_err>
        </bin>
        <bin id="62">
                <subbin>
                        <variable>q2da</variable>
                        <low_edge>400.0</low_edge>
                        <up_edge>1000.0</up_edge>
                </subbin>
                <subbin>
                        <variable>xda</variable>
                        <low_edge>0.02</low_edge>
                        <up_edge>0.1</up_edge>
                </subbin>
                <k_uds>1.20522</k_uds>
                <k_c>0.96703</k_c>
                <k_b>2.12221</k_b>
                <k_uds_err>0.056133</k_uds_err>
                <k_c_err>0.417855</k_c_err>
                <k_b_err>0.656013</k_b_err>
                <sigma_uds_true>0</sigma_uds_true>
                <sigma_c_true>34.6273</sigma_c_true>
                <sigma_b_true>2.31021</sigma_b_true>
                <sigma_uds>0</sigma_uds>
                <sigma_c>418.57</sigma_c>
                <sigma_b>61.2844</sigma_b>
                <sigma_uds_err>0</sigma_uds_err>
                <sigma_c_err>180.865</sigma_c_err>
                <sigma_b_err>18.9441</sigma_b_err>
        </bin>
        </bin_group>
</binning>